Workbook

Sheet Customers
A1: Customer ID | B1: Customer name | C1: Mobile no. | D1: POS (₹) | E1: Loan type | F1: Payment scheme | G1: Bullet: months of interest due | H1: Bullet: months bot should try to collect | I1: Monthly: months of interest unpaid | J1: Monthly: months to NPA | K1: Due amount (₹) | L1: Due since | M1: Risk tier | N1: Suggested channel | O1: Channel rationale | P1: Fallback channel | Q1: Treatment segment | R1: Suggested bot play | S1: Preferred language | T1: WhatsApp opt-in (Y/N) | U1: Preferred call window | V1: State | W1: City | X1: Branch | Y1: Loan account no. | Z1: Loan start date | AA1: Tenure (months) | AB1: Maturity date | AC1: Interest rate (% p.a.) | AD1: Monthly interest (₹) | AE1: Bot ask amount (₹) | AF1: Days past due | AG1: Last interest payment date | AH1: Days since last payment | AI1: eNACH registered | AJ1: Missed interest payments, last 6M | AK1: Broken promises-to-pay, last 3M | AL1: Bureau score | AM1: Off-us active loans (#) | AN1: Off-us delinquency (Y/N) | AO1: LTV (%) | AP1: Risk score (0-100) | AQ1: Last contact date | AR1: Last contact channel | AS1: Last contact outcome
A2: MFLC1000001 | B2: Shalini Joseph | C2: 9797186021 | D2: 83400 | E2: Gold loan | F2: Monthly interest | H2: =IF(F2="Bullet",MIN(G2,Assumptions!$B$6),"") | I2: 1 | J2: =IF(F2="Monthly interest",MAX(0,Assumptions!$B$5-I2),"") -> 2 | K2: =IF(F2="Bullet",G2*AD2,MAX(I2,1)*AD2) -> 1251 | L2: 46272 | M2: Low | N2: WhatsApp reminder | O2: Slipped regular payer: gentle digital nudge | P2: Voice bot | Q2: A - Regular monthly payer | R2: Gentle reminder + eNACH nudge | S2: Malayalam | T2: Y | U2: Afternoon (12-4pm) | V2: Kerala | W2: Kochi | X2: Kochi - Town Hall | Y2: GL9792667156 | Z2: 46180 | AA2: 24 | AB2: =EDATE(Z2,AA2) -> 46911 | AC2: 18 | AD2: =ROUND(D2*AC2/100/12,0) -> 1251 | AE2: =IF(F2="Bullet",H2*AD2,MIN(MAX(I2,1),Assumptions!$B$6)*AD2) -> 1251 | AF2: =IF(F2="Bullet",MAX(0,Assumptions!$B$4-AB2),MAX(0,Assumptions!$B$4-L2)) -> 26 | AG2: 46246 | AH2: =IF(AG2="","",Assumptions!$B$4-AG2) -> 52 | AI2: N | AJ2: 1 | AK2: 0 | AL2: 799 | AM2: 1 | AN2: N | AO2: 75 | AP2: 10 | AQ2: 46289 | AR2: WhatsApp reminder | AS2: Promised to pay
A3: MFLC1000002 | B3: Vasanthi Subramanian | C3: 7754456117 | D3: 252600 | E3: Gold loan | F3: Bullet | G3: 3 | H3: =IF(F3="Bullet",MIN(G3,Assumptions!$B$6),"") -> 2 | J3: =IF(F3="Monthly interest",MAX(0,Assumptions!$B$5-I3),"") | K3: =IF(F3="Bullet",G3*AD3,MAX(I3,1)*AD3) -> 7578 | L3: 46187 | M3: Medium | N3: Call center | O3: Early-stage delinquency: matched to risk and ticket size | P3: Field visit | Q3: E - Other early delinquent | R3: Reminder + payment link | S3: Tamil | T3: Y | U3: Afternoon (12-4pm) | V3: Tamil Nadu | W3: Tiruchirappalli | X3: Tiruchirappalli - MG Road | Y3: GL9546033474 | Z3: 46187 | AA3: 6 | AB3: =EDATE(Z3,AA3) -> 46370 | AC3: 12 | AD3: =ROUND(D3*AC3/100/12,0) -> 2526 | AE3: =IF(F3="Bullet",H3*AD3,MIN(MAX(I3,1),Assumptions!$B$6)*AD3) -> 5052 | AF3: =IF(F3="Bullet",MAX(0,Assumptions!$B$4-AB3),MAX(0,Assumptions!$B$4-L3)) -> 0 | AH3: =IF(AG3="","",Assumptions!$B$4-AG3) | AI3: NA | AK3: 1 | AL3: 618 | AM3: 0 | AN3: N | AO3: 65.1 | AP3: 36 | AQ3: 46293 | AR3: Voice bot | AS3: No response
A4: MFLC1000003 | B4: Seema Verma | C4: 6902921604 | D4: 68000 | E4: Gold loan | F4: Bullet | G4: 2 | H4: =IF(F4="Bullet",MIN(G4,Assumptions!$B$6),"") -> 2 | J4: =IF(F4="Monthly interest",MAX(0,Assumptions!$B$5-I4),"") | K4: =IF(F4="Bullet",G4*AD4,MAX(I4,1)*AD4) -> 2040 | L4: 46231 | M4: Low | N4: WhatsApp reminder | O4: Early-stage delinquency: matched to risk and ticket size | P4: Voice bot | Q4: E - Other early delinquent | R4: Reminder + payment link | S4: Hindi | T4: Y | U4: Evening (4-8pm) | V4: Rajasthan | W4: Kota | X4: Kota - Industrial Estate | Y4: GL0030869456 | Z4: 46231 | AA4: 12 | AB4: =EDATE(Z4,AA4) -> 46596 | AC4: 18 | AD4: =ROUND(D4*AC4/100/12,0) -> 1020 | AE4: =IF(F4="Bullet",H4*AD4,MIN(MAX(I4,1),Assumptions!$B$6)*AD4) -> 2040 | AF4: =IF(F4="Bullet",MAX(0,Assumptions!$B$4-AB4),MAX(0,Assumptions!$B$4-L4)) -> 0 | AH4: =IF(AG4="","",Assumptions!$B$4-AG4) | AI4: NA | AK4: 0 | AL4: 718 | AM4: 1 | AN4: N | AO4: 60 | AP4: 10 | AQ4: 46273 | AR4: Call center | AS4: Not reachable
A5: MFLC1000004 | B5: Pankaj Saxena | C5: 9381423040 | D5: 536700 | E5: Gold loan | F5: Monthly interest | H5: =IF(F5="Bullet",MIN(G5,Assumptions!$B$6),"") | I5: 1 | J5: =IF(F5="Monthly interest",MAX(0,Assumptions!$B$5-I5),"") -> 2 | K5: =IF(F5="Bullet",G5*AD5,MAX(I5,1)*AD5) -> 7156 | L5: 46278 | M5: Medium | N5: Voice bot | O5: No WhatsApp opt-in: routed to voice bot | P5: Call center | Q5: A - Regular monthly payer | R5: Gentle reminder + eNACH nudge | S5: Hindi | T5: N | U5: Evening (4-8pm) | V5: Uttar Pradesh | W5: Lucknow | X5: Lucknow - MG Road | Y5: GL9542959698 | Z5: 46155 | AA5: 24 | AB5: =EDATE(Z5,AA5) -> 46886 | AC5: 16 | AD5: =ROUND(D5*AC5/100/12,0) -> 7156 | AE5: =IF(F5="Bullet",H5*AD5,MIN(MAX(I5,1),Assumptions!$B$6)*AD5) -> 7156 | AF5: =IF(F5="Bullet",MAX(0,Assumptions!$B$4-AB5),MAX(0,Assumptions!$B$4-L5)) -> 20 | AG5: 46250 | AH5: =IF(AG5="","",Assumptions!$B$4-AG5) -> 48 | AI5: N | AJ5: 1 | AK5: 0 | AL5: 595 | AM5: 1 | AN5: N | AO5: 64.7 | AP5: 46 | AQ5: 46277 | AR5: Voice bot | AS5: No response
A6: MFLC1000005 | B6: Anitha Krishnan | C6: 7720933052 | D6: 109200 | E6: Gold loan | F6: Monthly interest | H6: =IF(F6="Bullet",MIN(G6,Assumptions!$B$6),"") | I6: 1 | J6: =IF(F6="Monthly interest",MAX(0,Assumptions!$B$5-I6),"") -> 2 | K6: =IF(F6="Bullet",G6*AD6,MAX(I6,1)*AD6) -> 2002 | L6: 46272 | M6: Low | N6: Voice bot | O6: Escalated: no response on whatsapp reminder | P6: Call center | Q6: A - Regular monthly payer | R6: Gentle reminder + eNACH nudge | S6: Tamil | T6: N | U6: Morning (9am-12pm) | V6: Tamil Nadu | W6: Madurai | X6: Madurai - Industrial Estate | Y6: GL2661127241 | Z6: 46180 | AA6: 12 | AB6: =EDATE(Z6,AA6) -> 46545 | AC6: 22 | AD6: =ROUND(D6*AC6/100/12,0) -> 2002 | AE6: =IF(F6="Bullet",H6*AD6,MIN(MAX(I6,1),Assumptions!$B$6)*AD6) -> 2002 | AF6: =IF(F6="Bullet",MAX(0,Assumptions!$B$4-AB6),MAX(0,Assumptions!$B$4-L6)) -> 26 | AG6: 46243 | AH6: =IF(AG6="","",Assumptions!$B$4-AG6) -> 55 | AI6: N | AJ6: 1 | AK6: 0 | AL6: 762 | AM6: 0 | AN6: N | AO6: 72 | AP6: 18 | AQ6: 46293 | AR6: WhatsApp reminder | AS6: No response
A7: MFLC1000006 | B7: Mani Raman | C7: 8986476026 | D7: 99900 | E7: Gold loan | F7: Monthly interest | H7: =IF(F7="Bullet",MIN(G7,Assumptions!$B$6),"") | I7: 1 | J7: =IF(F7="Monthly interest",MAX(0,Assumptions!$B$5-I7),"") -> 2 | K7: =IF(F7="Bullet",G7*AD7,MAX(I7,1)*AD7) -> 1998 | L7: 46289 | M7: Low | N7: WhatsApp reminder | O7: Slipped regular payer: gentle digital nudge | P7: Voice bot | Q7: A - Regular monthly payer | R7: Gentle reminder + eNACH nudge | S7: Tamil | T7: Y | U7: Evening (4-8pm) | V7: Tamil Nadu | W7: Madurai | X7: Madurai - Gandhi Nagar | Y7: GL4351950475 | Z7: 46015 | AA7: 12 | AB7: =EDATE(Z7,AA7) -> 46380 | AC7: 24 | AD7: =ROUND(D7*AC7/100/12,0) -> 1998 | AE7: =IF(F7="Bullet",H7*AD7,MIN(MAX(I7,1),Assumptions!$B$6)*AD7) -> 1998 | AF7: =IF(F7="Bullet",MAX(0,Assumptions!$B$4-AB7),MAX(0,Assumptions!$B$4-L7)) -> 9 | AG7: 46259 | AH7: =IF(AG7="","",Assumptions!$B$4-AG7) -> 39 | AI7: N | AJ7: 1 | AK7: 0 | AL7: 722 | AM7: 0 | AN7: N | AO7: 70.3 | AP7: 22 | AQ7: 46289 | AR7: Voice bot | AS7: No response
A8: MFLC1000007 | B8: Manoj Philip | C8: 7146416958 | D8: 127200 | E8: Gold loan | F8: Monthly interest | H8: =IF(F8="Bullet",MIN(G8,Assumptions!$B$6),"") | I8: 2 | J8: =IF(F8="Monthly interest",MAX(0,Assumptions!$B$5-I8),"") -> 1 | K8: =IF(F8="Bullet",G8*AD8,MAX(I8,1)*AD8) -> 3816 | L8: 46250 | M8: High | N8: Bot + call center | O8: Bouncing EII, high risk and high POS: bot first, call center for non-responders | P8: Field visit | Q8: D - Bouncing EII | R8: Reminder + part-payment negotiation, call center follow-up | S8: Malayalam | T8: Y | U8: Afternoon (12-4pm) | V8: Kerala | W8: Kochi | X8: Kochi - Station Road | Y8: GL4435519153 | Z8: 46069 | AA8: 24 | AB8: =EDATE(Z8,AA8) -> 46799 | AC8: 18 | AD8: =ROUND(D8*AC8/100/12,0) -> 1908 | AE8: =IF(F8="Bullet",H8*AD8,MIN(MAX(I8,1),Assumptions!$B$6)*AD8) -> 3816 | AF8: =IF(F8="Bullet",MAX(0,Assumptions!$B$4-AB8),MAX(0,Assumptions!$B$4-L8)) -> 48 | AG8: 46222 | AH8: =IF(AG8="","",Assumptions!$B$4-AG8) -> 76 | AI8: N | AJ8: 2 | AK8: 0 | AL8: 698 | AM8: 1 | AN8: N | AO8: 88 | AP8: 53 | AQ8: 46276 | AR8: Call center | AS8: Not reachable
A9: MFLC1000008 | B9: Biju Warrier | C9: 8709494509 | D9: 108900 | E9: Gold loan | F9: Monthly interest | H9: =IF(F9="Bullet",MIN(G9,Assumptions!$B$6),"") | I9: 1 | J9: =IF(F9="Monthly interest",MAX(0,Assumptions!$B$5-I9),"") -> 2 | K9: =IF(F9="Bullet",G9*AD9,MAX(I9,1)*AD9) -> 1271 | L9: 46298 | M9: Medium | N9: WhatsApp reminder | O9: Slipped regular payer: gentle digital nudge | P9: Voice bot | Q9: A - Regular monthly payer | R9: Gentle reminder + eNACH nudge | S9: Malayalam | T9: Y | U9: Morning (9am-12pm) | V9: Kerala | W9: Kottayam | X9: Kottayam - Station Road | Y9: GL8524472682 | Z9: 46025 | AA9: 24 | AB9: =EDATE(Z9,AA9) -> 46755 | AC9: 14 | AD9: =ROUND(D9*AC9/100/12,0) -> 1271 | AE9: =IF(F9="Bullet",H9*AD9,MIN(MAX(I9,1),Assumptions!$B$6)*AD9) -> 1271 | AF9: =IF(F9="Bullet",MAX(0,Assumptions!$B$4-AB9),MAX(0,Assumptions!$B$4-L9)) -> 0 | AG9: 46268 | AH9: =IF(AG9="","",Assumptions!$B$4-AG9) -> 30 | AI9: N | AJ9: 2 | AK9: 0 | AL9: 592 | AM9: 5 | AN9: N | AO9: 67.6 | AP9: 45 | AQ9: 46274 | AR9: WhatsApp reminder | AS9: Promised to pay
A10: MFLC1000009 | B10: Sunita Verma | C10: 7255797438 | D10: 52300 | E10: Gold loan | F10: Monthly interest | H10: =IF(F10="Bullet",MIN(G10,Assumptions!$B$6),"") | I10: 1 | J10: =IF(F10="Monthly interest",MAX(0,Assumptions!$B$5-I10),"") -> 2 | K10: =IF(F10="Bullet",G10*AD10,MAX(I10,1)*AD10) -> 785 | L10: 46289 | M10: Low | N10: Voice bot | O10: Escalated: not reachable on whatsapp reminder | P10: WhatsApp reminder | Q10: A - Regular monthly payer | R10: Gentle reminder + eNACH nudge | S10: Hindi | T10: Y | U10: Afternoon (12-4pm) | V10: Madhya Pradesh | W10: Bhopal | X10: Bhopal - Gandhi Nagar | Y10: GL0754123055 | Z10: 46046 | AA10: 12 | AB10: =EDATE(Z10,AA10) -> 46411 | AC10: 18 | AD10: =ROUND(D10*AC10/100/12,0) -> 785 | AE10: =IF(F10="Bullet",H10*AD10,MIN(MAX(I10,1),Assumptions!$B$6)*AD10) -> 785 | AF10: =IF(F10="Bullet",MAX(0,Assumptions!$B$4-AB10),MAX(0,Assumptions!$B$4-L10)) -> 9 | AG10: 46263 | AH10: =IF(AG10="","",Assumptions!$B$4-AG10) -> 35 | AI10: N | AJ10: 2 | AK10: 0 | AL10: 711 | AM10: 1 | AN10: N | AO10: 66.3 | AP10: 29 | AQ10: 46279 | AR10: WhatsApp reminder | AS10: Not reachable
A11: MFLC1000010 | B11: Dinesh Rajan | C11: 8788948999 | D11: 102300 | E11: Gold loan | F11: Monthly interest | H11: =IF(F11="Bullet",MIN(G11,Assumptions!$B$6),"") | I11: 1 | J11: =IF(F11="Monthly interest",MAX(0,Assumptions!$B$5-I11),"") -> 2 | K11: =IF(F11="Bullet",G11*AD11,MAX(I11,1)*AD11) -> 1876 | L11: 46283 | M11: Low | N11: WhatsApp reminder | O11: Slipped regular payer: gentle digital nudge | P11: Voice bot | Q11: A - Regular monthly payer | R11: Gentle reminder + eNACH nudge | S11: Tamil | T11: Y | U11: Morning (9am-12pm) | V11: Tamil Nadu | W11: Erode | X11: Erode - Temple Street | Y11: GL3949811627 | Z11: 46191 | AA11: 12 | AB11: =EDATE(Z11,AA11) -> 46556 | AC11: 22 | AD11: =ROUND(D11*AC11/100/12,0) -> 1876 | AE11: =IF(F11="Bullet",H11*AD11,MIN(MAX(I11,1),Assumptions!$B$6)*AD11) -> 1876 | AF11: =IF(F11="Bullet",MAX(0,Assumptions!$B$4-AB11),MAX(0,Assumptions!$B$4-L11)) -> 15 | AG11: 46256 | AH11: =IF(AG11="","",Assumptions!$B$4-AG11) -> 42 | AI11: N | AJ11: 1 | AK11: 0 | AL11: 744 | AM11: 0 | AN11: N | AO11: 66.8 | AP11: 21 | AQ11: 46294 | AR11: WhatsApp reminder | AS11: Promised to pay
A12: MFLC1000011 | B12: Vignesh Pandian | C12: 8309834299 | D12: 152700 | E12: Gold loan | F12: Monthly interest | H12: =IF(F12="Bullet",MIN(G12,Assumptions!$B$6),"") | I12: 1 | J12: =IF(F12="Monthly interest",MAX(0,Assumptions!$B$5-I12),"") -> 2 | K12: =IF(F12="Bullet",G12*AD12,MAX(I12,1)*AD12) -> 2036 | L12: 46278 | M12: Low | N12: Voice bot | O12: Escalated: no response on whatsapp reminder | P12: WhatsApp reminder | Q12: A - Regular monthly payer | R12: Gentle reminder + eNACH nudge | S12: Tamil | T12: Y | U12: Evening (4-8pm) | V12: Tamil Nadu | W12: Salem | X12: Salem - Civil Lines | Y12: GL1282382861 | Z12: 46186 | AA12: 12 | AB12: =EDATE(Z12,AA12) -> 46551 | AC12: 16 | AD12: =ROUND(D12*AC12/100/12,0) -> 2036 | AE12: =IF(F12="Bullet",H12*AD12,MIN(MAX(I12,1),Assumptions!$B$6)*AD12) -> 2036 | AF12: =IF(F12="Bullet",MAX(0,Assumptions!$B$4-AB12),MAX(0,Assumptions!$B$4-L12)) -> 20 | AG12: 46249 | AH12: =IF(AG12="","",Assumptions!$B$4-AG12) -> 49 | AI12: Y | AJ12: 2 | AK12: 0 | AL12: 771 | AM12: 2 | AN12: N | AO12: 69.5 | AP12: 21 | AQ12: 46296 | AR12: WhatsApp reminder | AS12: No response
A13: MFLC1000012 | B13: Binu Kumar | C13: 9082381936 | D13: 44200 | E13: Gold loan | F13: Monthly interest | H13: =IF(F13="Bullet",MIN(G13,Assumptions!$B$6),"") | I13: 2 | J13: =IF(F13="Monthly interest",MAX(0,Assumptions!$B$5-I13),"") -> 1 | K13: =IF(F13="Bullet",G13*AD13,MAX(I13,1)*AD13) -> 1768 | L13: 46243 | M13: Medium | N13: Voice bot | O13: Small ticket: bot-only, human cost not justified | P13: None - bot retry cadence | Q13: B - Small-ticket | R13: Standard reminder (no human follow-up) | S13: Malayalam | T13: Y | U13: Evening (4-8pm) | V13: Kerala | W13: Kannur | X13: Kannur - MG Road | Y13: GL4330979590 | Z13: 46090 | AA13: 12 | AB13: =EDATE(Z13,AA13) -> 46455 | AC13: 24 | AD13: =ROUND(D13*AC13/100/12,0) -> 884 | AE13: =IF(F13="Bullet",H13*AD13,MIN(MAX(I13,1),Assumptions!$B$6)*AD13) -> 1768 | AF13: =IF(F13="Bullet",MAX(0,Assumptions!$B$4-AB13),MAX(0,Assumptions!$B$4-L13)) -> 55 | AG13: 46216 | AH13: =IF(AG13="","",Assumptions!$B$4-AG13) -> 82 | AI13: Y | AJ13: 2 | AK13: 0 | AL13: NA | AM13: 0 | AN13: N | AO13: 74 | AP13: 45 | AS13: No prior contact
A14: MFLC1000013 | B14: Revathi Chandran | C14: 8872810772 | D14: 169000 | E14: Gold loan | F14: Monthly interest | H14: =IF(F14="Bullet",MIN(G14,Assumptions!$B$6),"") | I14: 2 | J14: =IF(F14="Monthly interest",MAX(0,Assumptions!$B$5-I14),"") -> 1 | K14: =IF(F14="Bullet",G14*AD14,MAX(I14,1)*AD14) -> 5634 | L14: 46262 | M14: High | N14: Bot + call center | O14: Bouncing EII, high risk and high POS: bot first, call center for non-responders | P14: Field visit | Q14: D - Bouncing EII | R14: Reminder + part-payment negotiation, call center follow-up | S14: Tamil | T14: N | U14: Afternoon (12-4pm) | V14: Tamil Nadu | W14: Madurai | X14: Madurai - Bus Stand | Y14: GL9606392082 | Z14: 46170 | AA14: 12 | AB14: =EDATE(Z14,AA14) -> 46535 | AC14: 20 | AD14: =ROUND(D14*AC14/100/12,0) -> 2817 | AE14: =IF(F14="Bullet",H14*AD14,MIN(MAX(I14,1),Assumptions!$B$6)*AD14) -> 5634 | AF14: =IF(F14="Bullet",MAX(0,Assumptions!$B$4-AB14),MAX(0,Assumptions!$B$4-L14)) -> 36 | AG14: 46235 | AH14: =IF(AG14="","",Assumptions!$B$4-AG14) -> 63 | AI14: Y | AJ14: 3 | AK14: 2 | AL14: 664 | AM14: 0 | AN14: N | AO14: 80.6 | AP14: 59 | AQ14: 46292 | AR14: WhatsApp reminder | AS14: Promised to pay
A15: MFLC1000014 | B15: Amit Yadav | C15: 8119480099 | D15: 137300 | E15: Gold loan | F15: Bullet | G15: 5 | H15: =IF(F15="Bullet",MIN(G15,Assumptions!$B$6),"") -> 2 | J15: =IF(F15="Monthly interest",MAX(0,Assumptions!$B$5-I15),"") | K15: =IF(F15="Bullet",G15*AD15,MAX(I15,1)*AD15) -> 8580 | L15: 46132 | M15: Medium | N15: Voice bot | O15: Accrued bullet: bot negotiates minimum amount due | P15: Call center | Q15: C - Accrued bullet | R15: Negotiate minimum amount due | S15: Hindi | T15: Y | U15: Morning (9am-12pm) | V15: Uttar Pradesh | W15: Noida | X15: Noida - Civil Lines | Y15: GL0246801055 | Z15: 46132 | AA15: 12 | AB15: =EDATE(Z15,AA15) -> 46497 | AC15: 15 | AD15: =ROUND(D15*AC15/100/12,0) -> 1716 | AE15: =IF(F15="Bullet",H15*AD15,MIN(MAX(I15,1),Assumptions!$B$6)*AD15) -> 3432 | AF15: =IF(F15="Bullet",MAX(0,Assumptions!$B$4-AB15),MAX(0,Assumptions!$B$4-L15)) -> 0 | AH15: =IF(AG15="","",Assumptions!$B$4-AG15) | AI15: NA | AK15: 1 | AL15: NA | AM15: 0 | AN15: N | AO15: 85.4 | AP15: 45 | AQ15: 46283 | AR15: Call center | AS15: No response
A16: MFLC1000015 | B16: Manoj Yadav | C16: 9796435955 | D16: 186400 | E16: Gold loan | F16: Bullet | G16: 2 | H16: =IF(F16="Bullet",MIN(G16,Assumptions!$B$6),"") -> 2 | J16: =IF(F16="Monthly interest",MAX(0,Assumptions!$B$5-I16),"") | K16: =IF(F16="Bullet",G16*AD16,MAX(I16,1)*AD16) -> 4660 | L16: 46229 | M16: Medium | N16: Voice bot | O16: Early-stage delinquency: matched to risk and ticket size | P16: Call center | Q16: E - Other early delinquent | R16: Reminder + payment link | S16: Hindi | T16: Y | U16: Evening (4-8pm) | V16: Delhi | W16: New Delhi | X16: New Delhi - MG Road | Y16: GL1478969052 | Z16: 46229 | AA16: 12 | AB16: =EDATE(Z16,AA16) -> 46594 | AC16: 15 | AD16: =ROUND(D16*AC16/100/12,0) -> 2330 | AE16: =IF(F16="Bullet",H16*AD16,MIN(MAX(I16,1),Assumptions!$B$6)*AD16) -> 4660 | AF16: =IF(F16="Bullet",MAX(0,Assumptions!$B$4-AB16),MAX(0,Assumptions!$B$4-L16)) -> 0 | AH16: =IF(AG16="","",Assumptions!$B$4-AG16) | AI16: NA | AK16: 0 | AL16: 645 | AM16: 2 | AN16: N | AO16: 66.2 | AP16: 31 | AQ16: 46274 | AR16: Field visit | AS16: Part payment made
A17: MFLC1000016 | B17: Bhavani Raju | C17: 9080104980 | D17: 149300 | E17: Gold loan | F17: Monthly interest | H17: =IF(F17="Bullet",MIN(G17,Assumptions!$B$6),"") | I17: 1 | J17: =IF(F17="Monthly interest",MAX(0,Assumptions!$B$5-I17),"") -> 2 | K17: =IF(F17="Bullet",G17*AD17,MAX(I17,1)*AD17) -> 1991 | L17: 46286 | M17: Low | N17: WhatsApp reminder | O17: Slipped regular payer: gentle digital nudge | P17: Voice bot | Q17: A - Regular monthly payer | R17: Gentle reminder + eNACH nudge | S17: Telugu | T17: Y | U17: Evening (4-8pm) | V17: Telangana | W17: Hyderabad | X17: Hyderabad - Nehru Nagar | Y17: GL6982532854 | Z17: 46133 | AA17: 12 | AB17: =EDATE(Z17,AA17) -> 46498 | AC17: 16 | AD17: =ROUND(D17*AC17/100/12,0) -> 1991 | AE17: =IF(F17="Bullet",H17*AD17,MIN(MAX(I17,1),Assumptions!$B$6)*AD17) -> 1991 | AF17: =IF(F17="Bullet",MAX(0,Assumptions!$B$4-AB17),MAX(0,Assumptions!$B$4-L17)) -> 12 | AG17: 46259 | AH17: =IF(AG17="","",Assumptions!$B$4-AG17) -> 39 | AI17: N | AJ17: 2 | AK17: 0 | AL17: 680 | AM17: 0 | AN17: N | AO17: 63 | AP17: 24 | AQ17: 46284 | AR17: Call center | AS17: Needs more time
A18: MFLC1000017 | B18: Divya Nair | C18: 7558224304 | D18: 93400 | E18: Gold loan | F18: Monthly interest | H18: =IF(F18="Bullet",MIN(G18,Assumptions!$B$6),"") | I18: 1 | J18: =IF(F18="Monthly interest",MAX(0,Assumptions!$B$5-I18),"") -> 2 | K18: =IF(F18="Bullet",G18*AD18,MAX(I18,1)*AD18) -> 1168 | L18: 46288 | M18: Low | N18: WhatsApp reminder | O18: Slipped regular payer: gentle digital nudge | P18: Voice bot | Q18: A - Regular monthly payer | R18: Gentle reminder + eNACH nudge | S18: Malayalam | T18: Y | U18: Afternoon (12-4pm) | V18: Kerala | W18: Kollam | X18: Kollam - Civil Lines | Y18: GL9539029181 | Z18: 46014 | AA18: 12 | AB18: =EDATE(Z18,AA18) -> 46379 | AC18: 15 | AD18: =ROUND(D18*AC18/100/12,0) -> 1168 | AE18: =IF(F18="Bullet",H18*AD18,MIN(MAX(I18,1),Assumptions!$B$6)*AD18) -> 1168 | AF18: =IF(F18="Bullet",MAX(0,Assumptions!$B$4-AB18),MAX(0,Assumptions!$B$4-L18)) -> 10 | AG18: 46260 | AH18: =IF(AG18="","",Assumptions!$B$4-AG18) -> 38 | AI18: N | AJ18: 1 | AK18: 0 | AL18: 731 | AM18: 1 | AN18: N | AO18: 62.5 | AP18: 17 | AS18: No prior contact
A19: MFLC1000018 | B19: Sravani Yadav | C19: 9068783467 | D19: 94700 | E19: Gold loan | F19: Bullet | G19: 4 | H19: =IF(F19="Bullet",MIN(G19,Assumptions!$B$6),"") -> 2 | J19: =IF(F19="Monthly interest",MAX(0,Assumptions!$B$5-I19),"") | K19: =IF(F19="Bullet",G19*AD19,MAX(I19,1)*AD19) -> 5684 | L19: 46175 | M19: Medium | N19: Voice bot | O19: Early-stage delinquency: matched to risk and ticket size | P19: Call center | Q19: E - Other early delinquent | R19: Reminder + payment link | S19: Telugu | T19: N | U19: Evening (4-8pm) | V19: Andhra Pradesh | W19: Tirupati | X19: Tirupati - Market Road | Y19: GL3712670973 | Z19: 46175 | AA19: 12 | AB19: =EDATE(Z19,AA19) -> 46540 | AC19: 18 | AD19: =ROUND(D19*AC19/100/12,0) -> 1421 | AE19: =IF(F19="Bullet",H19*AD19,MIN(MAX(I19,1),Assumptions!$B$6)*AD19) -> 2842 | AF19: =IF(F19="Bullet",MAX(0,Assumptions!$B$4-AB19),MAX(0,Assumptions!$B$4-L19)) -> 0 | AH19: =IF(AG19="","",Assumptions!$B$4-AG19) | AI19: NA | AK19: 1 | AL19: NA | AM19: 0 | AN19: N | AO19: 77.6 | AP19: 33 | AQ19: 46297 | AR19: WhatsApp reminder | AS19: No response
A20: MFLC1000019 | B20: Amit Tiwari | C20: 8559229999 | D20: 294600 | E20: Gold loan | F20: Bullet | G20: 3 | H20: =IF(F20="Bullet",MIN(G20,Assumptions!$B$6),"") -> 2 | J20: =IF(F20="Monthly interest",MAX(0,Assumptions!$B$5-I20),"") | K20: =IF(F20="Bullet",G20*AD20,MAX(I20,1)*AD20) -> 13257 | L20: 46194 | M20: High | N20: Bot + call center | O20: High risk: bot first, call center follows up | P20: Field visit | Q20: E - Other early delinquent | R20: Reminder + payment link | S20: Hindi | T20: N | U20: Morning (9am-12pm) | V20: Delhi | W20: Rohini | X20: Rohini - Gandhi Nagar | Y20: GL0918654665 | Z20: 46194 | AA20: 3 | AB20: =EDATE(Z20,AA20) -> 46286 | AC20: 18 | AD20: =ROUND(D20*AC20/100/12,0) -> 4419 | AE20: =IF(F20="Bullet",H20*AD20,MIN(MAX(I20,1),Assumptions!$B$6)*AD20) -> 8838 | AF20: =IF(F20="Bullet",MAX(0,Assumptions!$B$4-AB20),MAX(0,Assumptions!$B$4-L20)) -> 12 | AH20: =IF(AG20="","",Assumptions!$B$4-AG20) | AI20: NA | AK20: 2 | AL20: 695 | AM20: 1 | AN20: Y | AO20: 63.2 | AP20: 57 | AS20: No prior contact
A21: MFLC1000020 | B21: Manjula Kumar | C21: 9046649004 | D21: 96200 | E21: Gold loan | F21: Bullet | G21: 2 | H21: =IF(F21="Bullet",MIN(G21,Assumptions!$B$6),"") -> 2 | J21: =IF(F21="Monthly interest",MAX(0,Assumptions!$B$5-I21),"") | K21: =IF(F21="Bullet",G21*AD21,MAX(I21,1)*AD21) -> 2886 | L21: 46218 | M21: Low | N21: Voice bot | O21: No WhatsApp opt-in: routed to voice bot | P21: Call center | Q21: E - Other early delinquent | R21: Reminder + payment link | S21: Kannada | T21: N | U21: Afternoon (12-4pm) | V21: Karnataka | W21: Davanagere | X21: Davanagere - Temple Street | Y21: GL6476427482 | Z21: 46218 | AA21: 12 | AB21: =EDATE(Z21,AA21) -> 46583 | AC21: 18 | AD21: =ROUND(D21*AC21/100/12,0) -> 1443 | AE21: =IF(F21="Bullet",H21*AD21,MIN(MAX(I21,1),Assumptions!$B$6)*AD21) -> 2886 | AF21: =IF(F21="Bullet",MAX(0,Assumptions!$B$4-AB21),MAX(0,Assumptions!$B$4-L21)) -> 0 | AH21: =IF(AG21="","",Assumptions!$B$4-AG21) | AI21: NA | AK21: 0 | AL21: 771 | AM21: 1 | AN21: N | AO21: 71.9 | AP21: 8 | AQ21: 46297 | AR21: Voice bot | AS21: Promised to pay
A22: MFLC1000021 | B22: Geeta Kumar | C22: 9193917782 | D22: 18200 | E22: Gold loan | F22: Monthly interest | H22: =IF(F22="Bullet",MIN(G22,Assumptions!$B$6),"") | I22: 1 | J22: =IF(F22="Monthly interest",MAX(0,Assumptions!$B$5-I22),"") -> 2 | K22: =IF(F22="Bullet",G22*AD22,MAX(I22,1)*AD22) -> 303 | L22: 46274 | M22: Low | N22: WhatsApp reminder | O22: Small ticket: bot-only, human cost not justified | P22: Voice bot | Q22: B - Small-ticket | R22: Standard reminder (no human follow-up) | S22: Hindi | T22: Y | U22: Afternoon (12-4pm) | V22: Delhi | W22: New Delhi | X22: New Delhi - Town Hall | Y22: GL9470625750 | Z22: 46212 | AA22: 18 | AB22: =EDATE(Z22,AA22) -> 46761 | AC22: 20 | AD22: =ROUND(D22*AC22/100/12,0) -> 303 | AE22: =IF(F22="Bullet",H22*AD22,MIN(MAX(I22,1),Assumptions!$B$6)*AD22) -> 303 | AF22: =IF(F22="Bullet",MAX(0,Assumptions!$B$4-AB22),MAX(0,Assumptions!$B$4-L22)) -> 24 | AG22: 46248 | AH22: =IF(AG22="","",Assumptions!$B$4-AG22) -> 50 | AI22: N | AJ22: 1 | AK22: 1 | AL22: 806 | AM22: 1 | AN22: N | AO22: 57.9 | AP22: 20 | AQ22: 46282 | AR22: WhatsApp reminder | AS22: Needs more time
A23: MFLC1000022 | B23: Sreejith Joseph | C23: 9719256659 | D23: 166500 | E23: Gold loan | F23: Bullet | G23: 3 | H23: =IF(F23="Bullet",MIN(G23,Assumptions!$B$6),"") -> 2 | J23: =IF(F23="Monthly interest",MAX(0,Assumptions!$B$5-I23),"") | K23: =IF(F23="Bullet",G23*AD23,MAX(I23,1)*AD23) -> 5412 | L23: 46202 | M23: Medium | N23: Voice bot | O23: Early-stage delinquency: matched to risk and ticket size | P23: Call center | Q23: E - Other early delinquent | R23: Reminder + payment link | S23: Malayalam | T23: Y | U23: Evening (4-8pm) | V23: Kerala | W23: Kollam | X23: Kollam - Temple Street | Y23: GL6502495025 | Z23: 46202 | AA23: 6 | AB23: =EDATE(Z23,AA23) -> 46385 | AC23: 13 | AD23: =ROUND(D23*AC23/100/12,0) -> 1804 | AE23: =IF(F23="Bullet",H23*AD23,MIN(MAX(I23,1),Assumptions!$B$6)*AD23) -> 3608 | AF23: =IF(F23="Bullet",MAX(0,Assumptions!$B$4-AB23),MAX(0,Assumptions!$B$4-L23)) -> 0 | AH23: =IF(AG23="","",Assumptions!$B$4-AG23) | AI23: NA | AK23: 2 | AL23: 665 | AM23: 2 | AN23: N | AO23: 65.6 | AP23: 43 | AQ23: 46284 | AR23: Call center | AS23: Not reachable
A24: MFLC1000023 | B24: Basavaraj Gowda | C24: 9332822706 | D24: 427100 | E24: Gold loan | F24: Bullet | G24: 2 | H24: =IF(F24="Bullet",MIN(G24,Assumptions!$B$6),"") -> 2 | J24: =IF(F24="Monthly interest",MAX(0,Assumptions!$B$5-I24),"") | K24: =IF(F24="Bullet",G24*AD24,MAX(I24,1)*AD24) -> 12814 | L24: 46223 | M24: Low | N24: Voice bot | O24: No WhatsApp opt-in: routed to voice bot | P24: Call center | Q24: E - Other early delinquent | R24: Reminder + payment link | S24: Kannada | T24: N | U24: Morning (9am-12pm) | V24: Karnataka | W24: Belagavi | X24: Belagavi - Nehru Nagar | Y24: GL4783217487 | Z24: 46223 | AA24: 12 | AB24: =EDATE(Z24,AA24) -> 46588 | AC24: 18 | AD24: =ROUND(D24*AC24/100/12,0) -> 6407 | AE24: =IF(F24="Bullet",H24*AD24,MIN(MAX(I24,1),Assumptions!$B$6)*AD24) -> 12814 | AF24: =IF(F24="Bullet",MAX(0,Assumptions!$B$4-AB24),MAX(0,Assumptions!$B$4-L24)) -> 0 | AH24: =IF(AG24="","",Assumptions!$B$4-AG24) | AI24: NA | AK24: 0 | AL24: 790 | AM24: 1 | AN24: N | AO24: 57.5 | AP24: 9 | AQ24: 46282 | AR24: WhatsApp reminder | AS24: Part payment made
A25: MFLC1000024 | B25: Anitha Krishnan | C25: 8993723080 | D25: 60900 | E25: Gold loan | F25: Monthly interest | H25: =IF(F25="Bullet",MIN(G25,Assumptions!$B$6),"") | I25: 2 | J25: =IF(F25="Monthly interest",MAX(0,Assumptions!$B$5-I25),"") -> 1 | K25: =IF(F25="Bullet",G25*AD25,MAX(I25,1)*AD25) -> 1624 | L25: 46239 | M25: High | N25: Bot + call center | O25: Bouncing EII, high risk and high POS: bot first, call center for non-responders | P25: Field visit | Q25: D - Bouncing EII | R25: Reminder + part-payment negotiation, call center follow-up | S25: Tamil | T25: Y | U25: Evening (4-8pm) | V25: Tamil Nadu | W25: Erode | X25: Erode - Nehru Nagar | Y25: GL8810965675 | Z25: 46147 | AA25: 18 | AB25: =EDATE(Z25,AA25) -> 46696 | AC25: 16 | AD25: =ROUND(D25*AC25/100/12,0) -> 812 | AE25: =IF(F25="Bullet",H25*AD25,MIN(MAX(I25,1),Assumptions!$B$6)*AD25) -> 1624 | AF25: =IF(F25="Bullet",MAX(0,Assumptions!$B$4-AB25),MAX(0,Assumptions!$B$4-L25)) -> 59 | AG25: 46213 | AH25: =IF(AG25="","",Assumptions!$B$4-AG25) -> 85 | AI25: N | AJ25: 3 | AK25: 0 | AL25: 604 | AM25: 1 | AN25: N | AO25: 69 | AP25: 54 | AQ25: 46285 | AR25: Voice bot | AS25: No response
A26: MFLC1000025 | B26: Kiran Reddy | C26: 7951786467 | D26: 412600 | E26: Gold loan | F26: Monthly interest | H26: =IF(F26="Bullet",MIN(G26,Assumptions!$B$6),"") | I26: 2 | J26: =IF(F26="Monthly interest",MAX(0,Assumptions!$B$5-I26),"") -> 1 | K26: =IF(F26="Bullet",G26*AD26,MAX(I26,1)*AD26) -> 15128 | L26: 46259 | M26: Medium | N26: Call center | O26: Early-stage delinquency: matched to risk and ticket size | P26: Field visit | Q26: E - Other early delinquent | R26: Reminder + payment link | S26: Kannada | T26: Y | U26: Afternoon (12-4pm) | V26: Karnataka | W26: Mysuru | X26: Mysuru - Church Road | Y26: GL0058500675 | Z26: 46047 | AA26: 12 | AB26: =EDATE(Z26,AA26) -> 46412 | AC26: 22 | AD26: =ROUND(D26*AC26/100/12,0) -> 7564 | AE26: =IF(F26="Bullet",H26*AD26,MIN(MAX(I26,1),Assumptions!$B$6)*AD26) -> 15128 | AF26: =IF(F26="Bullet",MAX(0,Assumptions!$B$4-AB26),MAX(0,Assumptions!$B$4-L26)) -> 39 | AG26: 46229 | AH26: =IF(AG26="","",Assumptions!$B$4-AG26) -> 69 | AI26: Y | AJ26: 2 | AK26: 0 | AL26: 763 | AM26: 4 | AN26: N | AO26: 72.9 | AP26: 46 | AQ26: 46290 | AR26: Call center | AS26: Promised to pay
A27: MFLC1000026 | B27: Mathew Ibrahim | C27: 9341626753 | D27: 202100 | E27: Gold loan | F27: Monthly interest | H27: =IF(F27="Bullet",MIN(G27,Assumptions!$B$6),"") | I27: 2 | J27: =IF(F27="Monthly interest",MAX(0,Assumptions!$B$5-I27),"") -> 1 | K27: =IF(F27="Bullet",G27*AD27,MAX(I27,1)*AD27) -> 4716 | L27: 46262 | M27: Medium | N27: Call center | O27: Early-stage delinquency: matched to risk and ticket size | P27: Field visit | Q27: E - Other early delinquent | R27: Reminder + payment link | S27: Malayalam | T27: Y | U27: Evening (4-8pm) | V27: Kerala | W27: Kollam | X27: Kollam - Market Road | Y27: GL6462712855 | Z27: 46109 | AA27: 18 | AB27: =EDATE(Z27,AA27) -> 46658 | AC27: 14 | AD27: =ROUND(D27*AC27/100/12,0) -> 2358 | AE27: =IF(F27="Bullet",H27*AD27,MIN(MAX(I27,1),Assumptions!$B$6)*AD27) -> 4716 | AF27: =IF(F27="Bullet",MAX(0,Assumptions!$B$4-AB27),MAX(0,Assumptions!$B$4-L27)) -> 36 | AG27: 46236 | AH27: =IF(AG27="","",Assumptions!$B$4-AG27) -> 62 | AI27: N | AJ27: 2 | AK27: 0 | AL27: 794 | AM27: 2 | AN27: N | AO27: 74.1 | AP27: 33 | AQ27: 46283 | AR27: Voice bot | AS27: Part payment made
A28: MFLC1000027 | B28: Sunita Yadav | C28: 8719932145 | D28: 362800 | E28: Gold loan | F28: Monthly interest | H28: =IF(F28="Bullet",MIN(G28,Assumptions!$B$6),"") | I28: 1 | J28: =IF(F28="Monthly interest",MAX(0,Assumptions!$B$5-I28),"") -> 2 | K28: =IF(F28="Bullet",G28*AD28,MAX(I28,1)*AD28) -> 5442 | L28: 46287 | M28: Low | N28: Voice bot | O28: Escalated: not reachable on whatsapp reminder | P28: Call center | Q28: A - Regular monthly payer | R28: Gentle reminder + eNACH nudge | S28: English | T28: N | U28: Evening (4-8pm) | V28: Rajasthan | W28: Jaipur | X28: Jaipur - Church Road | Y28: GL1936564806 | Z28: 46225 | AA28: 18 | AB28: =EDATE(Z28,AA28) -> 46774 | AC28: 18 | AD28: =ROUND(D28*AC28/100/12,0) -> 5442 | AE28: =IF(F28="Bullet",H28*AD28,MIN(MAX(I28,1),Assumptions!$B$6)*AD28) -> 5442 | AF28: =IF(F28="Bullet",MAX(0,Assumptions!$B$4-AB28),MAX(0,Assumptions!$B$4-L28)) -> 11 | AG28: 46261 | AH28: =IF(AG28="","",Assumptions!$B$4-AG28) -> 37 | AI28: Y | AJ28: 1 | AK28: 0 | AL28: 653 | AM28: 0 | AN28: N | AO28: 53.4 | AP28: 24 | AQ28: 46288 | AR28: WhatsApp reminder | AS28: Not reachable
A29: MFLC1000028 | B29: Kumar Subramanian | C29: 9681029771 | D29: 72100 | E29: Gold loan | F29: Bullet | G29: 4 | H29: =IF(F29="Bullet",MIN(G29,Assumptions!$B$6),"") -> 2 | J29: =IF(F29="Monthly interest",MAX(0,Assumptions!$B$5-I29),"") | K29: =IF(F29="Bullet",G29*AD29,MAX(I29,1)*AD29) -> 3844 | L29: 46165 | M29: Medium | N29: Voice bot | O29: Early-stage delinquency: matched to risk and ticket size | P29: Call center | Q29: E - Other early delinquent | R29: Reminder + payment link | S29: Tamil | T29: Y | U29: Morning (9am-12pm) | V29: Tamil Nadu | W29: Tiruchirappalli | X29: Tiruchirappalli - Industrial Estate | Y29: GL9939265329 | Z29: 46165 | AA29: 6 | AB29: =EDATE(Z29,AA29) -> 46349 | AC29: 16 | AD29: =ROUND(D29*AC29/100/12,0) -> 961 | AE29: =IF(F29="Bullet",H29*AD29,MIN(MAX(I29,1),Assumptions!$B$6)*AD29) -> 1922 | AF29: =IF(F29="Bullet",MAX(0,Assumptions!$B$4-AB29),MAX(0,Assumptions!$B$4-L29)) -> 0 | AH29: =IF(AG29="","",Assumptions!$B$4-AG29) | AI29: NA | AK29: 2 | AL29: 725 | AM29: 1 | AN29: N | AO29: 83.1 | AP29: 43 | AQ29: 46281 | AR29: Call center | AS29: No response
A30: MFLC1000029 | B30: Deepak Saxena | C30: 9089541812 | D30: 85600 | E30: Gold loan | F30: Bullet | G30: 4 | H30: =IF(F30="Bullet",MIN(G30,Assumptions!$B$6),"") -> 2 | J30: =IF(F30="Monthly interest",MAX(0,Assumptions!$B$5-I30),"") | K30: =IF(F30="Bullet",G30*AD30,MAX(I30,1)*AD30) -> 3424 | L30: 46158 | M30: Medium | N30: Voice bot | O30: Early-stage delinquency: matched to risk and ticket size | P30: Call center | Q30: E - Other early delinquent | R30: Reminder + payment link | S30: Hindi | T30: Y | U30: Evening (4-8pm) | V30: Uttar Pradesh | W30: Agra | X30: Agra - Bus Stand | Y30: GL4552223620 | Z30: 46158 | AA30: 6 | AB30: =EDATE(Z30,AA30) -> 46342 | AC30: 12 | AD30: =ROUND(D30*AC30/100/12,0) -> 856 | AE30: =IF(F30="Bullet",H30*AD30,MIN(MAX(I30,1),Assumptions!$B$6)*AD30) -> 1712 | AF30: =IF(F30="Bullet",MAX(0,Assumptions!$B$4-AB30),MAX(0,Assumptions!$B$4-L30)) -> 0 | AH30: =IF(AG30="","",Assumptions!$B$4-AG30) | AI30: NA | AK30: 0 | AL30: 626 | AM30: 3 | AN30: N | AO30: 65.2 | AP30: 33 | AQ30: 46286 | AR30: WhatsApp reminder | AS30: No response
A31: MFLC1000030 | B31: Rajesh Singh | C31: 8553565681 | D31: 291400 | E31: Gold loan | F31: Bullet | G31: 1 | H31: =IF(F31="Bullet",MIN(G31,Assumptions!$B$6),"") -> 1 | J31: =IF(F31="Monthly interest",MAX(0,Assumptions!$B$5-I31),"") | K31: =IF(F31="Bullet",G31*AD31,MAX(I31,1)*AD31) -> 2914 | L31: 46266 | M31: Low | N31: Call center | O31: Escalated: customer refused/disputed, needs a human | P31: Field visit | Q31: E - Other early delinquent | R31: Reminder + payment link | S31: Hindi | T31: Y | U31: Morning (9am-12pm) | V31: Uttar Pradesh | W31: Agra | X31: Agra - Nehru Nagar | Y31: GL1478481668 | Z31: 46266 | AA31: 6 | AB31: =EDATE(Z31,AA31) -> 46447 | AC31: 12 | AD31: =ROUND(D31*AC31/100/12,0) -> 2914 | AE31: =IF(F31="Bullet",H31*AD31,MIN(MAX(I31,1),Assumptions!$B$6)*AD31) -> 2914 | AF31: =IF(F31="Bullet",MAX(0,Assumptions!$B$4-AB31),MAX(0,Assumptions!$B$4-L31)) -> 0 | AH31: =IF(AG31="","",Assumptions!$B$4-AG31) | AI31: NA | AK31: 0 | AL31: 711 | AM31: 0 | AN31: N | AO31: 61.1 | AP31: 13 | AQ31: 46277 | AR31: WhatsApp reminder | AS31: Refused / disputed
A32: MFLC1000031 | B32: Manjunath Swamy | C32: 8361072923 | D32: 440600 | E32: Gold loan | F32: Bullet | G32: 3 | H32: =IF(F32="Bullet",MIN(G32,Assumptions!$B$6),"") -> 2 | J32: =IF(F32="Monthly interest",MAX(0,Assumptions!$B$5-I32),"") | K32: =IF(F32="Bullet",G32*AD32,MAX(I32,1)*AD32) -> 17625 | L32: 46206 | M32: Medium | N32: Call center | O32: Early-stage delinquency: matched to risk and ticket size | P32: Field visit | Q32: E - Other early delinquent | R32: Reminder + payment link | S32: English | T32: Y | U32: Evening (4-8pm) | V32: Karnataka | W32: Mangaluru | X32: Mangaluru - Market Road | Y32: GL7322714338 | Z32: 46206 | AA32: 3 | AB32: =EDATE(Z32,AA32) -> 46298 | AC32: 16 | AD32: =ROUND(D32*AC32/100/12,0) -> 5875 | AE32: =IF(F32="Bullet",H32*AD32,MIN(MAX(I32,1),Assumptions!$B$6)*AD32) -> 11750 | AF32: =IF(F32="Bullet",MAX(0,Assumptions!$B$4-AB32),MAX(0,Assumptions!$B$4-L32)) -> 0 | AH32: =IF(AG32="","",Assumptions!$B$4-AG32) | AI32: NA | AK32: 1 | AL32: 702 | AM32: 2 | AN32: N | AO32: 69.2 | AP32: 34 | AQ32: 46291 | AR32: Call center | AS32: No response
A33: MFLC1000032 | B33: Vidya Kumar | C33: 7982704459 | D33: 71200 | E33: Gold loan | F33: Bullet | G33: 3 | H33: =IF(F33="Bullet",MIN(G33,Assumptions!$B$6),"") -> 2 | J33: =IF(F33="Monthly interest",MAX(0,Assumptions!$B$5-I33),"") | K33: =IF(F33="Bullet",G33*AD33,MAX(I33,1)*AD33) -> 2847 | L33: 46191 | M33: Medium | N33: Voice bot | O33: Early-stage delinquency: matched to risk and ticket size | P33: Call center | Q33: E - Other early delinquent | R33: Reminder + payment link | S33: Kannada | T33: Y | U33: Afternoon (12-4pm) | V33: Karnataka | W33: Bengaluru | X33: Bengaluru - Civil Lines | Y33: GL6684780985 | Z33: 46191 | AA33: 3 | AB33: =EDATE(Z33,AA33) -> 46283 | AC33: 16 | AD33: =ROUND(D33*AC33/100/12,0) -> 949 | AE33: =IF(F33="Bullet",H33*AD33,MIN(MAX(I33,1),Assumptions!$B$6)*AD33) -> 1898 | AF33: =IF(F33="Bullet",MAX(0,Assumptions!$B$4-AB33),MAX(0,Assumptions!$B$4-L33)) -> 15 | AH33: =IF(AG33="","",Assumptions!$B$4-AG33) | AI33: NA | AK33: 2 | AL33: 751 | AM33: 1 | AN33: N | AO33: 63.3 | AP33: 31 | AQ33: 46273 | AR33: Call center | AS33: Not reachable
A34: MFLC1000033 | B34: Venkatesh Setty | C34: 8053611000 | D34: 36700 | E34: Gold loan | F34: Monthly interest | H34: =IF(F34="Bullet",MIN(G34,Assumptions!$B$6),"") | I34: 2 | J34: =IF(F34="Monthly interest",MAX(0,Assumptions!$B$5-I34),"") -> 1 | K34: =IF(F34="Bullet",G34*AD34,MAX(I34,1)*AD34) -> 1346 | L34: 46255 | M34: Medium | N34: Voice bot | O34: Small ticket: bot-only, human cost not justified | P34: None - bot retry cadence | Q34: B - Small-ticket | R34: Standard reminder (no human follow-up) | S34: Telugu | T34: Y | U34: Morning (9am-12pm) | V34: Telangana | W34: Hyderabad | X34: Hyderabad - Church Road | Y34: GL3169938950 | Z34: 46043 | AA34: 12 | AB34: =EDATE(Z34,AA34) -> 46408 | AC34: 22 | AD34: =ROUND(D34*AC34/100/12,0) -> 673 | AE34: =IF(F34="Bullet",H34*AD34,MIN(MAX(I34,1),Assumptions!$B$6)*AD34) -> 1346 | AF34: =IF(F34="Bullet",MAX(0,Assumptions!$B$4-AB34),MAX(0,Assumptions!$B$4-L34)) -> 43 | AG34: 46226 | AH34: =IF(AG34="","",Assumptions!$B$4-AG34) -> 72 | AI34: Y | AJ34: 3 | AK34: 0 | AL34: 776 | AM34: 2 | AN34: N | AO34: 70.2 | AP34: 35 | AQ34: 46281 | AR34: Call center | AS34: Promised to pay
A35: MFLC1000034 | B35: Fathima Varghese | C35: 7809424699 | D35: 67800 | E35: Gold loan | F35: Bullet | G35: 3 | H35: =IF(F35="Bullet",MIN(G35,Assumptions!$B$6),"") -> 2 | J35: =IF(F35="Monthly interest",MAX(0,Assumptions!$B$5-I35),"") | K35: =IF(F35="Bullet",G35*AD35,MAX(I35,1)*AD35) -> 3051 | L35: 46199 | M35: Low | N35: Call center | O35: Escalated: not reachable on voice bot | P35: Field visit | Q35: E - Other early delinquent | R35: Reminder + payment link | S35: Malayalam | T35: Y | U35: Morning (9am-12pm) | V35: Kerala | W35: Kollam | X35: Kollam - Market Road | Y35: GL6920690877 | Z35: 46199 | AA35: 12 | AB35: =EDATE(Z35,AA35) -> 46564 | AC35: 18 | AD35: =ROUND(D35*AC35/100/12,0) -> 1017 | AE35: =IF(F35="Bullet",H35*AD35,MIN(MAX(I35,1),Assumptions!$B$6)*AD35) -> 2034 | AF35: =IF(F35="Bullet",MAX(0,Assumptions!$B$4-AB35),MAX(0,Assumptions!$B$4-L35)) -> 0 | AH35: =IF(AG35="","",Assumptions!$B$4-AG35) | AI35: NA | AK35: 0 | AL35: 623 | AM35: 1 | AN35: N | AO35: 74.8 | AP35: 30 | AQ35: 46296 | AR35: Voice bot | AS35: Not reachable
A36: MFLC1000035 | B36: Faisal Panicker | C36: 7276352551 | D36: 497100 | E36: Gold loan | F36: Bullet | G36: 3 | H36: =IF(F36="Bullet",MIN(G36,Assumptions!$B$6),"") -> 2 | J36: =IF(F36="Monthly interest",MAX(0,Assumptions!$B$5-I36),"") | K36: =IF(F36="Bullet",G36*AD36,MAX(I36,1)*AD36) -> 14913 | L36: 46184 | M36: Low | N36: Voice bot | O36: Early-stage delinquency: matched to risk and ticket size | P36: WhatsApp reminder | Q36: E - Other early delinquent | R36: Reminder + payment link | S36: Malayalam | T36: Y | U36: Evening (4-8pm) | V36: Kerala | W36: Kozhikode | X36: Kozhikode - Temple Street | Y36: GL1841547189 | Z36: 46184 | AA36: 12 | AB36: =EDATE(Z36,AA36) -> 46549 | AC36: 12 | AD36: =ROUND(D36*AC36/100/12,0) -> 4971 | AE36: =IF(F36="Bullet",H36*AD36,MIN(MAX(I36,1),Assumptions!$B$6)*AD36) -> 9942 | AF36: =IF(F36="Bullet",MAX(0,Assumptions!$B$4-AB36),MAX(0,Assumptions!$B$4-L36)) -> 0 | AH36: =IF(AG36="","",Assumptions!$B$4-AG36) | AI36: NA | AK36: 1 | AL36: 700 | AM36: 1 | AN36: N | AO36: 80.2 | AP36: 30 | AQ36: 46295 | AR36: WhatsApp reminder | AS36: Not reachable
A37: MFLC1000036 | B37: Saranya Sundaram | C37: 8183376000 | D37: 75700 | E37: Gold loan | F37: Bullet | G37: 4 | H37: =IF(F37="Bullet",MIN(G37,Assumptions!$B$6),"") -> 2 | J37: =IF(F37="Monthly interest",MAX(0,Assumptions!$B$5-I37),"") | K37: =IF(F37="Bullet",G37*AD37,MAX(I37,1)*AD37) -> 3532 | L37: 46169 | M37: Low | N37: Voice bot | O37: Early-stage delinquency: matched to risk and ticket size | P37: WhatsApp reminder | Q37: E - Other early delinquent | R37: Reminder + payment link | S37: Tamil | T37: Y | U37: Evening (4-8pm) | V37: Tamil Nadu | W37: Coimbatore | X37: Coimbatore - Gandhi Nagar | Y37: GL1443957122 | Z37: 46169 | AA37: 12 | AB37: =EDATE(Z37,AA37) -> 46534 | AC37: 14 | AD37: =ROUND(D37*AC37/100/12,0) -> 883 | AE37: =IF(F37="Bullet",H37*AD37,MIN(MAX(I37,1),Assumptions!$B$6)*AD37) -> 1766 | AF37: =IF(F37="Bullet",MAX(0,Assumptions!$B$4-AB37),MAX(0,Assumptions!$B$4-L37)) -> 0 | AH37: =IF(AG37="","",Assumptions!$B$4-AG37) | AI37: NA | AK37: 1 | AL37: 703 | AM37: 1 | AN37: N | AO37: 75.4 | AP37: 28 | AQ37: 46279 | AR37: Call center | AS37: No response
A38: MFLC1000037 | B38: Rakesh Rathore | C38: 9996999531 | D38: 90900 | E38: Gold loan | F38: Bullet | G38: 1 | H38: =IF(F38="Bullet",MIN(G38,Assumptions!$B$6),"") -> 1 | J38: =IF(F38="Monthly interest",MAX(0,Assumptions!$B$5-I38),"") | K38: =IF(F38="Bullet",G38*AD38,MAX(I38,1)*AD38) -> 985 | L38: 46253 | M38: Low | N38: WhatsApp reminder | O38: Early-stage delinquency: matched to risk and ticket size | P38: Voice bot | Q38: E - Other early delinquent | R38: Reminder + payment link | S38: Hindi | T38: Y | U38: Evening (4-8pm) | V38: Delhi | W38: Rohini | X38: Rohini - Town Hall | Y38: GL1696318091 | Z38: 46253 | AA38: 12 | AB38: =EDATE(Z38,AA38) -> 46618 | AC38: 13 | AD38: =ROUND(D38*AC38/100/12,0) -> 985 | AE38: =IF(F38="Bullet",H38*AD38,MIN(MAX(I38,1),Assumptions!$B$6)*AD38) -> 985 | AF38: =IF(F38="Bullet",MAX(0,Assumptions!$B$4-AB38),MAX(0,Assumptions!$B$4-L38)) -> 0 | AH38: =IF(AG38="","",Assumptions!$B$4-AG38) | AI38: NA | AK38: 0 | AL38: 650 | AM38: 0 | AN38: N | AO38: 72.9 | AP38: 17 | AQ38: 46276 | AR38: Call center | AS38: No response
A39: MFLC1000038 | B39: Ramesh Yadav | C39: 9755530823 | D39: 145200 | E39: Gold loan | F39: Monthly interest | H39: =IF(F39="Bullet",MIN(G39,Assumptions!$B$6),"") | I39: 1 | J39: =IF(F39="Monthly interest",MAX(0,Assumptions!$B$5-I39),"") -> 2 | K39: =IF(F39="Bullet",G39*AD39,MAX(I39,1)*AD39) -> 1815 | L39: 46274 | M39: Low | N39: WhatsApp reminder | O39: Slipped regular payer: gentle digital nudge | P39: Voice bot | Q39: A - Regular monthly payer | R39: Gentle reminder + eNACH nudge | S39: Hindi | T39: Y | U39: Morning (9am-12pm) | V39: Madhya Pradesh | W39: Indore | X39: Indore - Temple Street | Y39: GL2604364267 | Z39: 46031 | AA39: 12 | AB39: =EDATE(Z39,AA39) -> 46396 | AC39: 15 | AD39: =ROUND(D39*AC39/100/12,0) -> 1815 | AE39: =IF(F39="Bullet",H39*AD39,MIN(MAX(I39,1),Assumptions!$B$6)*AD39) -> 1815 | AF39: =IF(F39="Bullet",MAX(0,Assumptions!$B$4-AB39),MAX(0,Assumptions!$B$4-L39)) -> 24 | AG39: 46244 | AH39: =IF(AG39="","",Assumptions!$B$4-AG39) -> 54 | AI39: Y | AJ39: 1 | AK39: 0 | AL39: 852 | AM39: 0 | AN39: N | AO39: 68.6 | AP39: 5 | AQ39: 46287 | AR39: WhatsApp reminder | AS39: Promised to pay
A40: MFLC1000039 | B40: Remya Warrier | C40: 9992563338 | D40: 82400 | E40: Gold loan | F40: Bullet | G40: 3 | H40: =IF(F40="Bullet",MIN(G40,Assumptions!$B$6),"") -> 2 | J40: =IF(F40="Monthly interest",MAX(0,Assumptions!$B$5-I40),"") | K40: =IF(F40="Bullet",G40*AD40,MAX(I40,1)*AD40) -> 3708 | L40: 46182 | M40: Low | N40: Voice bot | O40: Early-stage delinquency: matched to risk and ticket size | P40: WhatsApp reminder | Q40: E - Other early delinquent | R40: Reminder + payment link | S40: Malayalam | T40: Y | U40: Evening (4-8pm) | V40: Kerala | W40: Alappuzha | X40: Alappuzha - Temple Street | Y40: GL0657724044 | Z40: 46182 | AA40: 6 | AB40: =EDATE(Z40,AA40) -> 46365 | AC40: 18 | AD40: =ROUND(D40*AC40/100/12,0) -> 1236 | AE40: =IF(F40="Bullet",H40*AD40,MIN(MAX(I40,1),Assumptions!$B$6)*AD40) -> 2472 | AF40: =IF(F40="Bullet",MAX(0,Assumptions!$B$4-AB40),MAX(0,Assumptions!$B$4-L40)) -> 0 | AH40: =IF(AG40="","",Assumptions!$B$4-AG40) | AI40: NA | AK40: 1 | AL40: 729 | AM40: 0 | AN40: N | AO40: 73.9 | AP40: 14 | AS40: No prior contact
A41: MFLC1000040 | B41: Naresh Kumar | C41: 9209450820 | D41: 258300 | E41: Gold loan | F41: Bullet | G41: 3 | H41: =IF(F41="Bullet",MIN(G41,Assumptions!$B$6),"") -> 2 | J41: =IF(F41="Monthly interest",MAX(0,Assumptions!$B$5-I41),"") | K41: =IF(F41="Bullet",G41*AD41,MAX(I41,1)*AD41) -> 8394 | L41: 46205 | M41: Low | N41: Voice bot | O41: Early-stage delinquency: matched to risk and ticket size | P41: Call center | Q41: E - Other early delinquent | R41: Reminder + payment link | S41: Telugu | T41: N | U41: Morning (9am-12pm) | V41: Telangana | W41: Nizamabad | X41: Nizamabad - Nehru Nagar | Y41: GL2146312185 | Z41: 46205 | AA41: 6 | AB41: =EDATE(Z41,AA41) -> 46389 | AC41: 13 | AD41: =ROUND(D41*AC41/100/12,0) -> 2798 | AE41: =IF(F41="Bullet",H41*AD41,MIN(MAX(I41,1),Assumptions!$B$6)*AD41) -> 5596 | AF41: =IF(F41="Bullet",MAX(0,Assumptions!$B$4-AB41),MAX(0,Assumptions!$B$4-L41)) -> 0 | AH41: =IF(AG41="","",Assumptions!$B$4-AG41) | AI41: NA | AK41: 1 | AL41: 727 | AM41: 3 | AN41: N | AO41: 66.7 | AP41: 26 | AQ41: 46289 | AR41: Voice bot | AS41: Part payment made
A42: MFLC1000041 | B42: Rani Mathew | C42: 7304140490 | D42: 28000 | E42: Gold loan | F42: Bullet | G42: 2 | H42: =IF(F42="Bullet",MIN(G42,Assumptions!$B$6),"") -> 2 | J42: =IF(F42="Monthly interest",MAX(0,Assumptions!$B$5-I42),"") | K42: =IF(F42="Bullet",G42*AD42,MAX(I42,1)*AD42) -> 560 | L42: 46221 | M42: Medium | N42: Voice bot | O42: Small ticket: bot-only, human cost not justified | P42: None - bot retry cadence | Q42: B - Small-ticket | R42: Standard reminder (no human follow-up) | S42: Malayalam | T42: N | U42: Afternoon (12-4pm) | V42: Kerala | W42: Kochi | X42: Kochi - Market Road | Y42: GL6561975192 | Z42: 46221 | AA42: 6 | AB42: =EDATE(Z42,AA42) -> 46405 | AC42: 12 | AD42: =ROUND(D42*AC42/100/12,0) -> 280 | AE42: =IF(F42="Bullet",H42*AD42,MIN(MAX(I42,1),Assumptions!$B$6)*AD42) -> 560 | AF42: =IF(F42="Bullet",MAX(0,Assumptions!$B$4-AB42),MAX(0,Assumptions!$B$4-L42)) -> 0 | AH42: =IF(AG42="","",Assumptions!$B$4-AG42) | AI42: NA | AK42: 0 | AL42: NA | AM42: 1 | AN42: N | AO42: 87.8 | AP42: 32 | AQ42: 46296 | AR42: Voice bot | AS42: No response
A43: MFLC1000042 | B43: Thomas Joseph | C43: 7416524098 | D43: 109200 | E43: Gold loan | F43: Monthly interest | H43: =IF(F43="Bullet",MIN(G43,Assumptions!$B$6),"") | I43: 1 | J43: =IF(F43="Monthly interest",MAX(0,Assumptions!$B$5-I43),"") -> 2 | K43: =IF(F43="Bullet",G43*AD43,MAX(I43,1)*AD43) -> 2184 | L43: 46298 | M43: High | N43: Bot + call center | O43: Bouncing EII, high risk and high POS: bot first, call center for non-responders | P43: Field visit | Q43: D - Bouncing EII | R43: Reminder + part-payment negotiation, call center follow-up | S43: Malayalam | T43: Y | U43: Afternoon (12-4pm) | V43: Kerala | W43: Alappuzha | X43: Alappuzha - Industrial Estate | Y43: GL8382014509 | Z43: 46176 | AA43: 24 | AB43: =EDATE(Z43,AA43) -> 46907 | AC43: 24 | AD43: =ROUND(D43*AC43/100/12,0) -> 2184 | AE43: =IF(F43="Bullet",H43*AD43,MIN(MAX(I43,1),Assumptions!$B$6)*AD43) -> 2184 | AF43: =IF(F43="Bullet",MAX(0,Assumptions!$B$4-AB43),MAX(0,Assumptions!$B$4-L43)) -> 0 | AG43: 46271 | AH43: =IF(AG43="","",Assumptions!$B$4-AG43) -> 27 | AI43: N | AJ43: 1 | AK43: 0 | AL43: 563 | AM43: 1 | AN43: N | AO43: 84.1 | AP43: 56 | AQ43: 46282 | AR43: Voice bot | AS43: No response
A44: MFLC1000043 | B44: Sunita Jain | C44: 7660992824 | D44: 266300 | E44: Gold loan | F44: Monthly interest | H44: =IF(F44="Bullet",MIN(G44,Assumptions!$B$6),"") | I44: 2 | J44: =IF(F44="Monthly interest",MAX(0,Assumptions!$B$5-I44),"") -> 1 | K44: =IF(F44="Bullet",G44*AD44,MAX(I44,1)*AD44) -> 9764 | L44: 46238 | M44: Medium | N44: Call center | O44: Early-stage delinquency: matched to risk and ticket size | P44: Field visit | Q44: E - Other early delinquent | R44: Reminder + payment link | S44: Hindi | T44: Y | U44: Evening (4-8pm) | V44: Delhi | W44: Dwarka | X44: Dwarka - Gandhi Nagar | Y44: GL1272222340 | Z44: 46177 | AA44: 12 | AB44: =EDATE(Z44,AA44) -> 46542 | AC44: 22 | AD44: =ROUND(D44*AC44/100/12,0) -> 4882 | AE44: =IF(F44="Bullet",H44*AD44,MIN(MAX(I44,1),Assumptions!$B$6)*AD44) -> 9764 | AF44: =IF(F44="Bullet",MAX(0,Assumptions!$B$4-AB44),MAX(0,Assumptions!$B$4-L44)) -> 60 | AG44: 46211 | AH44: =IF(AG44="","",Assumptions!$B$4-AG44) -> 87 | AI44: N | AJ44: 2 | AK44: 0 | AL44: 627 | AM44: 0 | AN44: N | AO44: 63.8 | AP44: 47 | AS44: No prior contact
A45: MFLC1000044 | B45: Geetha Swamy | C45: 7307426548 | D45: 96000 | E45: Gold loan | F45: Bullet | G45: 1 | H45: =IF(F45="Bullet",MIN(G45,Assumptions!$B$6),"") -> 1 | J45: =IF(F45="Monthly interest",MAX(0,Assumptions!$B$5-I45),"") | K45: =IF(F45="Bullet",G45*AD45,MAX(I45,1)*AD45) -> 1040 | L45: 46264 | M45: Low | N45: WhatsApp reminder | O45: Early-stage delinquency: matched to risk and ticket size | P45: Voice bot | Q45: E - Other early delinquent | R45: Reminder + payment link | S45: English | T45: Y | U45: Evening (4-8pm) | V45: Karnataka | W45: Davanagere | X45: Davanagere - Gandhi Nagar | Y45: GL8931424293 | Z45: 46264 | AA45: 6 | AB45: =EDATE(Z45,AA45) -> 46446 | AC45: 13 | AD45: =ROUND(D45*AC45/100/12,0) -> 1040 | AE45: =IF(F45="Bullet",H45*AD45,MIN(MAX(I45,1),Assumptions!$B$6)*AD45) -> 1040 | AF45: =IF(F45="Bullet",MAX(0,Assumptions!$B$4-AB45),MAX(0,Assumptions!$B$4-L45)) -> 0 | AH45: =IF(AG45="","",Assumptions!$B$4-AG45) | AI45: NA | AK45: 0 | AL45: 723 | AM45: 1 | AN45: N | AO45: 68.2 | AP45: 8 | AQ45: 46277 | AR45: WhatsApp reminder | AS45: Needs more time
A46: MFLC1000045 | B46: Vikas Jain | C46: 9320437296 | D46: 103600 | E46: Gold loan | F46: Monthly interest | H46: =IF(F46="Bullet",MIN(G46,Assumptions!$B$6),"") | I46: 2 | J46: =IF(F46="Monthly interest",MAX(0,Assumptions!$B$5-I46),"") -> 1 | K46: =IF(F46="Bullet",G46*AD46,MAX(I46,1)*AD46) -> 3108 | L46: 46241 | M46: Medium | N46: Voice bot | O46: Early-stage delinquency: matched to risk and ticket size | P46: Call center | Q46: E - Other early delinquent | R46: Reminder + payment link | S46: Hindi | T46: Y | U46: Evening (4-8pm) | V46: Madhya Pradesh | W46: Bhopal | X46: Bhopal - Industrial Estate | Y46: GL7696987901 | Z46: 46119 | AA46: 18 | AB46: =EDATE(Z46,AA46) -> 46667 | AC46: 18 | AD46: =ROUND(D46*AC46/100/12,0) -> 1554 | AE46: =IF(F46="Bullet",H46*AD46,MIN(MAX(I46,1),Assumptions!$B$6)*AD46) -> 3108 | AF46: =IF(F46="Bullet",MAX(0,Assumptions!$B$4-AB46),MAX(0,Assumptions!$B$4-L46)) -> 57 | AG46: 46213 | AH46: =IF(AG46="","",Assumptions!$B$4-AG46) -> 85 | AI46: Y | AJ46: 3 | AK46: 2 | AL46: 728 | AM46: 1 | AN46: N | AO46: 64.7 | AP46: 46 | AQ46: 46286 | AR46: Voice bot | AS46: Promised to pay
A47: MFLC1000046 | B47: Ajay Kumar | C47: 9628749563 | D47: 324500 | E47: Gold loan | F47: Monthly interest | H47: =IF(F47="Bullet",MIN(G47,Assumptions!$B$6),"") | I47: 2 | J47: =IF(F47="Monthly interest",MAX(0,Assumptions!$B$5-I47),"") -> 1 | K47: =IF(F47="Bullet",G47*AD47,MAX(I47,1)*AD47) -> 8654 | L47: 46261 | M47: Medium | N47: Call center | O47: Early-stage delinquency: matched to risk and ticket size | P47: Field visit | Q47: E - Other early delinquent | R47: Reminder + payment link | S47: Hindi | T47: Y | U47: Morning (9am-12pm) | V47: Rajasthan | W47: Jodhpur | X47: Jodhpur - Church Road | Y47: GL3994023691 | Z47: 46200 | AA47: 18 | AB47: =EDATE(Z47,AA47) -> 46748 | AC47: 16 | AD47: =ROUND(D47*AC47/100/12,0) -> 4327 | AE47: =IF(F47="Bullet",H47*AD47,MIN(MAX(I47,1),Assumptions!$B$6)*AD47) -> 8654 | AF47: =IF(F47="Bullet",MAX(0,Assumptions!$B$4-AB47),MAX(0,Assumptions!$B$4-L47)) -> 37 | AG47: 46230 | AH47: =IF(AG47="","",Assumptions!$B$4-AG47) -> 68 | AI47: Y | AJ47: 2 | AK47: 2 | AL47: 782 | AM47: 0 | AN47: N | AO47: 61.4 | AP47: 35 | AQ47: 46282 | AR47: Call center | AS47: Promised to pay
A48: MFLC1000047 | B48: Harish Shankar | C48: 9651421119 | D48: 93600 | E48: Gold loan | F48: Monthly interest | H48: =IF(F48="Bullet",MIN(G48,Assumptions!$B$6),"") | I48: 1 | J48: =IF(F48="Monthly interest",MAX(0,Assumptions!$B$5-I48),"") -> 2 | K48: =IF(F48="Bullet",G48*AD48,MAX(I48,1)*AD48) -> 1248 | L48: 46282 | M48: Low | N48: WhatsApp reminder | O48: Slipped regular payer: gentle digital nudge | P48: Voice bot | Q48: A - Regular monthly payer | R48: Gentle reminder + eNACH nudge | S48: Kannada | T48: Y | U48: Evening (4-8pm) | V48: Karnataka | W48: Mysuru | X48: Mysuru - Church Road | Y48: GL8222256885 | Z48: 46070 | AA48: 12 | AB48: =EDATE(Z48,AA48) -> 46435 | AC48: 16 | AD48: =ROUND(D48*AC48/100/12,0) -> 1248 | AE48: =IF(F48="Bullet",H48*AD48,MIN(MAX(I48,1),Assumptions!$B$6)*AD48) -> 1248 | AF48: =IF(F48="Bullet",MAX(0,Assumptions!$B$4-AB48),MAX(0,Assumptions!$B$4-L48)) -> 16 | AG48: 46252 | AH48: =IF(AG48="","",Assumptions!$B$4-AG48) -> 46 | AI48: N | AJ48: 1 | AK48: 0 | AL48: 673 | AM48: 0 | AN48: N | AO48: 63.9 | AP48: 29 | AQ48: 46289 | AR48: Voice bot | AS48: Promised to pay
A49: MFLC1000048 | B49: Mani Ravi | C49: 7611344919 | D49: 76600 | E49: Gold loan | F49: Monthly interest | H49: =IF(F49="Bullet",MIN(G49,Assumptions!$B$6),"") | I49: 1 | J49: =IF(F49="Monthly interest",MAX(0,Assumptions!$B$5-I49),"") -> 2 | K49: =IF(F49="Bullet",G49*AD49,MAX(I49,1)*AD49) -> 894 | L49: 46278 | M49: Medium | N49: WhatsApp reminder | O49: Slipped regular payer: gentle digital nudge | P49: Voice bot | Q49: A - Regular monthly payer | R49: Gentle reminder + eNACH nudge | S49: Tamil | T49: Y | U49: Morning (9am-12pm) | V49: Tamil Nadu | W49: Coimbatore | X49: Coimbatore - Bus Stand | Y49: GL1878369358 | Z49: 46125 | AA49: 12 | AB49: =EDATE(Z49,AA49) -> 46490 | AC49: 14 | AD49: =ROUND(D49*AC49/100/12,0) -> 894 | AE49: =IF(F49="Bullet",H49*AD49,MIN(MAX(I49,1),Assumptions!$B$6)*AD49) -> 894 | AF49: =IF(F49="Bullet",MAX(0,Assumptions!$B$4-AB49),MAX(0,Assumptions!$B$4-L49)) -> 20 | AG49: 46248 | AH49: =IF(AG49="","",Assumptions!$B$4-AG49) -> 50 | AI49: N | AJ49: 1 | AK49: 0 | AL49: NA | AM49: 3 | AN49: N | AO49: 81.5 | AP49: 36 | AQ49: 46294 | AR49: Voice bot | AS49: No response
A50: MFLC1000049 | B50: Radha Varma | C50: 9500833661 | D50: 164600 | E50: Gold loan | F50: Monthly interest | H50: =IF(F50="Bullet",MIN(G50,Assumptions!$B$6),"") | I50: 1 | J50: =IF(F50="Monthly interest",MAX(0,Assumptions!$B$5-I50),"") -> 2 | K50: =IF(F50="Bullet",G50*AD50,MAX(I50,1)*AD50) -> 2195 | L50: 46298 | M50: Low | N50: WhatsApp reminder | O50: Slipped regular payer: gentle digital nudge | P50: Voice bot | Q50: A - Regular monthly payer | R50: Gentle reminder + eNACH nudge | S50: Telugu | T50: Y | U50: Evening (4-8pm) | V50: Telangana | W50: Warangal | X50: Warangal - Gandhi Nagar | Y50: GL5242673346 | Z50: 46237 | AA50: 12 | AB50: =EDATE(Z50,AA50) -> 46602 | AC50: 16 | AD50: =ROUND(D50*AC50/100/12,0) -> 2195 | AE50: =IF(F50="Bullet",H50*AD50,MIN(MAX(I50,1),Assumptions!$B$6)*AD50) -> 2195 | AF50: =IF(F50="Bullet",MAX(0,Assumptions!$B$4-AB50),MAX(0,Assumptions!$B$4-L50)) -> 0 | AG50: 46273 | AH50: =IF(AG50="","",Assumptions!$B$4-AG50) -> 25 | AI50: N | AJ50: 2 | AK50: 0 | AL50: 698 | AM50: 2 | AN50: N | AO50: 54.1 | AP50: 27 | AQ50: 46279 | AR50: Call center | AS50: No response
A51: MFLC1000050 | B51: Ganesh Subramanian | C51: 8285000513 | D51: 540500 | E51: Gold loan | F51: Bullet | G51: 4 | H51: =IF(F51="Bullet",MIN(G51,Assumptions!$B$6),"") -> 2 | J51: =IF(F51="Monthly interest",MAX(0,Assumptions!$B$5-I51),"") | K51: =IF(F51="Bullet",G51*AD51,MAX(I51,1)*AD51) -> 27024 | L51: 46162 | M51: Low | N51: Voice bot | O51: Early-stage delinquency: matched to risk and ticket size | P51: WhatsApp reminder | Q51: E - Other early delinquent | R51: Reminder + payment link | S51: Tamil | T51: Y | U51: Morning (9am-12pm) | V51: Tamil Nadu | W51: Tirunelveli | X51: Tirunelveli - Bus Stand | Y51: GL9243172716 | Z51: 46162 | AA51: 12 | AB51: =EDATE(Z51,AA51) -> 46527 | AC51: 15 | AD51: =ROUND(D51*AC51/100/12,0) -> 6756 | AE51: =IF(F51="Bullet",H51*AD51,MIN(MAX(I51,1),Assumptions!$B$6)*AD51) -> 13512 | AF51: =IF(F51="Bullet",MAX(0,Assumptions!$B$4-AB51),MAX(0,Assumptions!$B$4-L51)) -> 0 | AH51: =IF(AG51="","",Assumptions!$B$4-AG51) | AI51: NA | AK51: 2 | AL51: 809 | AM51: 1 | AN51: N | AO51: 54.3 | AP51: 27 | AQ51: 46292 | AR51: WhatsApp reminder | AS51: No response
A52: MFLC1000051 | B52: Kavita Kumar | C52: 9712959036 | D52: 90700 | E52: Gold loan | F52: Bullet | G52: 3 | H52: =IF(F52="Bullet",MIN(G52,Assumptions!$B$6),"") -> 2 | J52: =IF(F52="Monthly interest",MAX(0,Assumptions!$B$5-I52),"") | K52: =IF(F52="Bullet",G52*AD52,MAX(I52,1)*AD52) -> 3402 | L52: 46183 | M52: Low | N52: Voice bot | O52: Early-stage delinquency: matched to risk and ticket size | P52: WhatsApp reminder | Q52: E - Other early delinquent | R52: Reminder + payment link | S52: Hindi | T52: Y | U52: Evening (4-8pm) | V52: Delhi | W52: Dwarka | X52: Dwarka - Civil Lines | Y52: GL4847582713 | Z52: 46183 | AA52: 6 | AB52: =EDATE(Z52,AA52) -> 46366 | AC52: 15 | AD52: =ROUND(D52*AC52/100/12,0) -> 1134 | AE52: =IF(F52="Bullet",H52*AD52,MIN(MAX(I52,1),Assumptions!$B$6)*AD52) -> 2268 | AF52: =IF(F52="Bullet",MAX(0,Assumptions!$B$4-AB52),MAX(0,Assumptions!$B$4-L52)) -> 0 | AH52: =IF(AG52="","",Assumptions!$B$4-AG52) | AI52: NA | AK52: 0 | AL52: 786 | AM52: 0 | AN52: N | AO52: 77.6 | AP52: 8 | AQ52: 46277 | AR52: Voice bot | AS52: Needs more time
A53: MFLC1000052 | B53: Karthik Rajan | C53: 7012444841 | D53: 27000 | E53: Gold loan | F53: Bullet | G53: 1 | H53: =IF(F53="Bullet",MIN(G53,Assumptions!$B$6),"") -> 1 | J53: =IF(F53="Monthly interest",MAX(0,Assumptions!$B$5-I53),"") | K53: =IF(F53="Bullet",G53*AD53,MAX(I53,1)*AD53) -> 293 | L53: 46268 | M53: Low | N53: WhatsApp reminder | O53: Small ticket: bot-only, human cost not justified | P53: Voice bot | Q53: B - Small-ticket | R53: Standard reminder (no human follow-up) | S53: Tamil | T53: Y | U53: Evening (4-8pm) | V53: Tamil Nadu | W53: Erode | X53: Erode - Main Road | Y53: GL5930363560 | Z53: 46268 | AA53: 6 | AB53: =EDATE(Z53,AA53) -> 46449 | AC53: 13 | AD53: =ROUND(D53*AC53/100/12,0) -> 293 | AE53: =IF(F53="Bullet",H53*AD53,MIN(MAX(I53,1),Assumptions!$B$6)*AD53) -> 293 | AF53: =IF(F53="Bullet",MAX(0,Assumptions!$B$4-AB53),MAX(0,Assumptions!$B$4-L53)) -> 0 | AH53: =IF(AG53="","",Assumptions!$B$4-AG53) | AI53: NA | AK53: 0 | AL53: 721 | AM53: 1 | AN53: N | AO53: 69.4 | AP53: 7 | AQ53: 46280 | AR53: WhatsApp reminder | AS53: Promised to pay
A54: MFLC1000053 | B54: Harish Kumar | C54: 8132759271 | D54: 336100 | E54: Gold loan | F54: Bullet | G54: 1 | H54: =IF(F54="Bullet",MIN(G54,Assumptions!$B$6),"") -> 1 | J54: =IF(F54="Monthly interest",MAX(0,Assumptions!$B$5-I54),"") | K54: =IF(F54="Bullet",G54*AD54,MAX(I54,1)*AD54) -> 3641 | L54: 46246 | M54: Low | N54: Voice bot | O54: Escalated: no response on whatsapp reminder | P54: WhatsApp reminder | Q54: E - Other early delinquent | R54: Reminder + payment link | S54: Kannada | T54: Y | U54: Morning (9am-12pm) | V54: Karnataka | W54: Bengaluru | X54: Bengaluru - Main Road | Y54: GL0688440029 | Z54: 46246 | AA54: 6 | AB54: =EDATE(Z54,AA54) -> 46430 | AC54: 13 | AD54: =ROUND(D54*AC54/100/12,0) -> 3641 | AE54: =IF(F54="Bullet",H54*AD54,MIN(MAX(I54,1),Assumptions!$B$6)*AD54) -> 3641 | AF54: =IF(F54="Bullet",MAX(0,Assumptions!$B$4-AB54),MAX(0,Assumptions!$B$4-L54)) -> 0 | AH54: =IF(AG54="","",Assumptions!$B$4-AG54) | AI54: NA | AK54: 0 | AL54: 668 | AM54: 0 | AN54: N | AO54: 70 | AP54: 17 | AQ54: 46282 | AR54: WhatsApp reminder | AS54: No response
A55: MFLC1000054 | B55: Anil Rathore | C55: 9861961563 | D55: 119200 | E55: Gold loan | F55: Bullet | G55: 1 | H55: =IF(F55="Bullet",MIN(G55,Assumptions!$B$6),"") -> 1 | J55: =IF(F55="Monthly interest",MAX(0,Assumptions!$B$5-I55),"") | K55: =IF(F55="Bullet",G55*AD55,MAX(I55,1)*AD55) -> 1589 | L55: 46259 | M55: Low | N55: Call center | O55: Escalated: customer refused/disputed, needs a human | P55: Field visit | Q55: E - Other early delinquent | R55: Reminder + payment link | S55: Hindi | T55: Y | U55: Morning (9am-12pm) | V55: Uttar Pradesh | W55: Lucknow | X55: Lucknow - Market Road | Y55: GL7834564504 | Z55: 46259 | AA55: 12 | AB55: =EDATE(Z55,AA55) -> 46624 | AC55: 16 | AD55: =ROUND(D55*AC55/100/12,0) -> 1589 | AE55: =IF(F55="Bullet",H55*AD55,MIN(MAX(I55,1),Assumptions!$B$6)*AD55) -> 1589 | AF55: =IF(F55="Bullet",MAX(0,Assumptions!$B$4-AB55),MAX(0,Assumptions!$B$4-L55)) -> 0 | AH55: =IF(AG55="","",Assumptions!$B$4-AG55) | AI55: NA | AK55: 0 | AL55: NA | AM55: 0 | AN55: N | AO55: 59.5 | AP55: 9 | AQ55: 46275 | AR55: WhatsApp reminder | AS55: Refused / disputed
A56: MFLC1000055 | B56: Mary Joseph | C56: 9950344032 | D56: 128200 | E56: Gold loan | F56: Monthly interest | H56: =IF(F56="Bullet",MIN(G56,Assumptions!$B$6),"") | I56: 2 | J56: =IF(F56="Monthly interest",MAX(0,Assumptions!$B$5-I56),"") -> 1 | K56: =IF(F56="Bullet",G56*AD56,MAX(I56,1)*AD56) -> 2992 | L56: 46239 | M56: High | N56: Bot + call center | O56: Bouncing EII, high risk and high POS: bot first, call center for non-responders | P56: Field visit | Q56: D - Bouncing EII | R56: Reminder + part-payment negotiation, call center follow-up | S56: Malayalam | T56: Y | U56: Evening (4-8pm) | V56: Kerala | W56: Kochi | X56: Kochi - Nehru Nagar | Y56: GL4376664313 | Z56: 45966 | AA56: 12 | AB56: =EDATE(Z56,AA56) -> 46331 | AC56: 14 | AD56: =ROUND(D56*AC56/100/12,0) -> 1496 | AE56: =IF(F56="Bullet",H56*AD56,MIN(MAX(I56,1),Assumptions!$B$6)*AD56) -> 2992 | AF56: =IF(F56="Bullet",MAX(0,Assumptions!$B$4-AB56),MAX(0,Assumptions!$B$4-L56)) -> 59 | AG56: 46210 | AH56: =IF(AG56="","",Assumptions!$B$4-AG56) -> 88 | AI56: N | AJ56: 2 | AK56: 0 | AL56: 636 | AM56: 3 | AN56: N | AO56: 64 | AP56: 57 | AQ56: 46283 | AR56: Call center | AS56: No response
A57: MFLC1000056 | B57: Kumar Raman | C57: 9661871999 | D57: 26700 | E57: Gold loan | F57: Monthly interest | H57: =IF(F57="Bullet",MIN(G57,Assumptions!$B$6),"") | I57: 2 | J57: =IF(F57="Monthly interest",MAX(0,Assumptions!$B$5-I57),"") -> 1 | K57: =IF(F57="Bullet",G57*AD57,MAX(I57,1)*AD57) -> 980 | L57: 46247 | M57: Medium | N57: Voice bot | O57: Small ticket: bot-only, human cost not justified | P57: None - bot retry cadence | Q57: B - Small-ticket | R57: Standard reminder (no human follow-up) | S57: English | T57: Y | U57: Evening (4-8pm) | V57: Tamil Nadu | W57: Coimbatore | X57: Coimbatore - Civil Lines | Y57: GL3958870179 | Z57: 45974 | AA57: 18 | AB57: =EDATE(Z57,AA57) -> 46520 | AC57: 22 | AD57: =ROUND(D57*AC57/100/12,0) -> 490 | AE57: =IF(F57="Bullet",H57*AD57,MIN(MAX(I57,1),Assumptions!$B$6)*AD57) -> 980 | AF57: =IF(F57="Bullet",MAX(0,Assumptions!$B$4-AB57),MAX(0,Assumptions!$B$4-L57)) -> 51 | AG57: 46217 | AH57: =IF(AG57="","",Assumptions!$B$4-AG57) -> 81 | AI57: Y | AJ57: 2 | AK57: 0 | AL57: 803 | AM57: 0 | AN57: N | AO57: 70.6 | AP57: 32 | AQ57: 46274 | AR57: Call center | AS57: Promised to pay
A58: MFLC1000057 | B58: Suresh Mathew | C58: 9641832176 | D58: 195400 | E58: Gold loan | F58: Bullet | G58: 2 | H58: =IF(F58="Bullet",MIN(G58,Assumptions!$B$6),"") -> 2 | J58: =IF(F58="Monthly interest",MAX(0,Assumptions!$B$5-I58),"") | K58: =IF(F58="Bullet",G58*AD58,MAX(I58,1)*AD58) -> 5210 | L58: 46220 | M58: Low | N58: Call center | O58: Escalated: customer refused/disputed, needs a human | P58: Field visit | Q58: E - Other early delinquent | R58: Reminder + payment link | S58: Malayalam | T58: Y | U58: Evening (4-8pm) | V58: Kerala | W58: Thiruvananthapuram | X58: Thiruvananthapuram - Industrial Estate | Y58: GL1726451224 | Z58: 46220 | AA58: 12 | AB58: =EDATE(Z58,AA58) -> 46585 | AC58: 16 | AD58: =ROUND(D58*AC58/100/12,0) -> 2605 | AE58: =IF(F58="Bullet",H58*AD58,MIN(MAX(I58,1),Assumptions!$B$6)*AD58) -> 5210 | AF58: =IF(F58="Bullet",MAX(0,Assumptions!$B$4-AB58),MAX(0,Assumptions!$B$4-L58)) -> 0 | AH58: =IF(AG58="","",Assumptions!$B$4-AG58) | AI58: NA | AK58: 1 | AL58: 747 | AM58: 2 | AN58: N | AO58: 54.8 | AP58: 16 | AQ58: 46279 | AR58: WhatsApp reminder | AS58: Refused / disputed
A59: MFLC1000058 | B59: Mary Joseph | C59: 6550546958 | D59: 83000 | E59: Gold loan | F59: Monthly interest | H59: =IF(F59="Bullet",MIN(G59,Assumptions!$B$6),"") | I59: 2 | J59: =IF(F59="Monthly interest",MAX(0,Assumptions!$B$5-I59),"") -> 1 | K59: =IF(F59="Bullet",G59*AD59,MAX(I59,1)*AD59) -> 2490 | L59: 46266 | M59: High | N59: Bot + call center | O59: Bouncing EII, high risk and high POS: bot first, call center for non-responders | P59: Field visit | Q59: D - Bouncing EII | R59: Reminder + part-payment negotiation, call center follow-up | S59: Malayalam | T59: N | U59: Evening (4-8pm) | V59: Kerala | W59: Kottayam | X59: Kottayam - Town Hall | Y59: GL8181115066 | Z59: 46023 | AA59: 12 | AB59: =EDATE(Z59,AA59) -> 46388 | AC59: 18 | AD59: =ROUND(D59*AC59/100/12,0) -> 1245 | AE59: =IF(F59="Bullet",H59*AD59,MIN(MAX(I59,1),Assumptions!$B$6)*AD59) -> 2490 | AF59: =IF(F59="Bullet",MAX(0,Assumptions!$B$4-AB59),MAX(0,Assumptions!$B$4-L59)) -> 32 | AG59: 46237 | AH59: =IF(AG59="","",Assumptions!$B$4-AG59) -> 61 | AI59: N | AJ59: 3 | AK59: 0 | AL59: 686 | AM59: 0 | AN59: Y | AO59: 68.5 | AP59: 61 | AQ59: 46281 | AR59: Voice bot | AS59: Not reachable
A60: MFLC1000059 | B60: Suresh Chowdary | C60: 8311017075 | D60: 248900 | E60: Gold loan | F60: Bullet | G60: 3 | H60: =IF(F60="Bullet",MIN(G60,Assumptions!$B$6),"") -> 2 | J60: =IF(F60="Monthly interest",MAX(0,Assumptions!$B$5-I60),"") | K60: =IF(F60="Bullet",G60*AD60,MAX(I60,1)*AD60) -> 7467 | L60: 46196 | M60: Low | N60: Voice bot | O60: Early-stage delinquency: matched to risk and ticket size | P60: Call center | Q60: E - Other early delinquent | R60: Reminder + payment link | S60: Telugu | T60: N | U60: Afternoon (12-4pm) | V60: Andhra Pradesh | W60: Tirupati | X60: Tirupati - Civil Lines | Y60: GL9595876155 | Z60: 46196 | AA60: 12 | AB60: =EDATE(Z60,AA60) -> 46561 | AC60: 12 | AD60: =ROUND(D60*AC60/100/12,0) -> 2489 | AE60: =IF(F60="Bullet",H60*AD60,MIN(MAX(I60,1),Assumptions!$B$6)*AD60) -> 4978 | AF60: =IF(F60="Bullet",MAX(0,Assumptions!$B$4-AB60),MAX(0,Assumptions!$B$4-L60)) -> 0 | AH60: =IF(AG60="","",Assumptions!$B$4-AG60) | AI60: NA | AK60: 1 | AL60: 816 | AM60: 2 | AN60: N | AO60: 67.9 | AP60: 15 | AQ60: 46275 | AR60: Call center | AS60: No response
A61: MFLC1000060 | B61: Anjaneyulu Murthy | C61: 6383237912 | D61: 164600 | E61: Gold loan | F61: Bullet | G61: 2 | H61: =IF(F61="Bullet",MIN(G61,Assumptions!$B$6),"") -> 2 | J61: =IF(F61="Monthly interest",MAX(0,Assumptions!$B$5-I61),"") | K61: =IF(F61="Bullet",G61*AD61,MAX(I61,1)*AD61) -> 4938 | L61: 46220 | M61: Medium | N61: Voice bot | O61: Early-stage delinquency: matched to risk and ticket size | P61: Call center | Q61: E - Other early delinquent | R61: Reminder + payment link | S61: Telugu | T61: N | U61: Evening (4-8pm) | V61: Andhra Pradesh | W61: Visakhapatnam | X61: Visakhapatnam - Town Hall | Y61: GL2328889478 | Z61: 46220 | AA61: 3 | AB61: =EDATE(Z61,AA61) -> 46312 | AC61: 18 | AD61: =ROUND(D61*AC61/100/12,0) -> 2469 | AE61: =IF(F61="Bullet",H61*AD61,MIN(MAX(I61,1),Assumptions!$B$6)*AD61) -> 4938 | AF61: =IF(F61="Bullet",MAX(0,Assumptions!$B$4-AB61),MAX(0,Assumptions!$B$4-L61)) -> 0 | AH61: =IF(AG61="","",Assumptions!$B$4-AG61) | AI61: NA | AK61: 0 | AL61: 616 | AM61: 0 | AN61: N | AO61: 72.5 | AP61: 38 | AQ61: 46292 | AR61: Call center | AS61: Promised to pay
A62: MFLC1000061 | B62: Amit Chauhan | C62: 9360321305 | D62: 125700 | E62: Gold loan | F62: Monthly interest | H62: =IF(F62="Bullet",MIN(G62,Assumptions!$B$6),"") | I62: 1 | J62: =IF(F62="Monthly interest",MAX(0,Assumptions!$B$5-I62),"") -> 2 | K62: =IF(F62="Bullet",G62*AD62,MAX(I62,1)*AD62) -> 2095 | L62: 46292 | M62: Low | N62: WhatsApp reminder | O62: Slipped regular payer: gentle digital nudge | P62: Voice bot | Q62: A - Regular monthly payer | R62: Gentle reminder + eNACH nudge | S62: Hindi | T62: Y | U62: Morning (9am-12pm) | V62: Uttar Pradesh | W62: Agra | X62: Agra - Market Road | Y62: GL8079199308 | Z62: 46108 | AA62: 12 | AB62: =EDATE(Z62,AA62) -> 46473 | AC62: 20 | AD62: =ROUND(D62*AC62/100/12,0) -> 2095 | AE62: =IF(F62="Bullet",H62*AD62,MIN(MAX(I62,1),Assumptions!$B$6)*AD62) -> 2095 | AF62: =IF(F62="Bullet",MAX(0,Assumptions!$B$4-AB62),MAX(0,Assumptions!$B$4-L62)) -> 6 | AG62: 46264 | AH62: =IF(AG62="","",Assumptions!$B$4-AG62) -> 34 | AI62: Y | AJ62: 1 | AK62: 0 | AL62: 681 | AM62: 2 | AN62: N | AO62: 64.7 | AP62: 23 | AQ62: 46276 | AR62: Voice bot | AS62: No response
A63: MFLC1000062 | B63: Murugan Chandran | C63: 9323706394 | D63: 53400 | E63: Gold loan | F63: Bullet | G63: 4 | H63: =IF(F63="Bullet",MIN(G63,Assumptions!$B$6),"") -> 2 | J63: =IF(F63="Monthly interest",MAX(0,Assumptions!$B$5-I63),"") | K63: =IF(F63="Bullet",G63*AD63,MAX(I63,1)*AD63) -> 3204 | L63: 46158 | M63: Medium | N63: Voice bot | O63: Early-stage delinquency: matched to risk and ticket size | P63: Call center | Q63: E - Other early delinquent | R63: Reminder + payment link | S63: Tamil | T63: Y | U63: Evening (4-8pm) | V63: Tamil Nadu | W63: Vellore | X63: Vellore - Market Road | Y63: GL9942428903 | Z63: 46158 | AA63: 3 | AB63: =EDATE(Z63,AA63) -> 46250 | AC63: 18 | AD63: =ROUND(D63*AC63/100/12,0) -> 801 | AE63: =IF(F63="Bullet",H63*AD63,MIN(MAX(I63,1),Assumptions!$B$6)*AD63) -> 1602 | AF63: =IF(F63="Bullet",MAX(0,Assumptions!$B$4-AB63),MAX(0,Assumptions!$B$4-L63)) -> 48 | AH63: =IF(AG63="","",Assumptions!$B$4-AG63) | AI63: NA | AK63: 0 | AL63: 644 | AM63: 0 | AN63: N | AO63: 68 | AP63: 40 | AQ63: 46287 | AR63: Call center | AS63: No response
A64: MFLC1000063 | B64: Smitha Pillai | C64: 6000923612 | D64: 16900 | E64: Gold loan | F64: Monthly interest | H64: =IF(F64="Bullet",MIN(G64,Assumptions!$B$6),"") | I64: 2 | J64: =IF(F64="Monthly interest",MAX(0,Assumptions!$B$5-I64),"") -> 1 | K64: =IF(F64="Bullet",G64*AD64,MAX(I64,1)*AD64) -> 422 | L64: 46267 | M64: High | N64: Bot + call center | O64: High risk (small ticket): bot first, call center follows up | P64: Field visit | Q64: B - Small-ticket | R64: Standard reminder (no human follow-up) | S64: Malayalam | T64: Y | U64: Evening (4-8pm) | V64: Kerala | W64: Kannur | X64: Kannur - Temple Street | Y64: GL9992453020 | Z64: 45993 | AA64: 12 | AB64: =EDATE(Z64,AA64) -> 46358 | AC64: 15 | AD64: =ROUND(D64*AC64/100/12,0) -> 211 | AE64: =IF(F64="Bullet",H64*AD64,MIN(MAX(I64,1),Assumptions!$B$6)*AD64) -> 422 | AF64: =IF(F64="Bullet",MAX(0,Assumptions!$B$4-AB64),MAX(0,Assumptions!$B$4-L64)) -> 31 | AG64: 46236 | AH64: =IF(AG64="","",Assumptions!$B$4-AG64) -> 62 | AI64: Y | AJ64: 2 | AK64: 1 | AL64: 673 | AM64: 0 | AN64: N | AO64: 70.5 | AP64: 51 | AS64: No prior contact
A65: MFLC1000064 | B65: Pankaj Pandey | C65: 7349154224 | D65: 197600 | E65: Gold loan | F65: Bullet | G65: 4 | H65: =IF(F65="Bullet",MIN(G65,Assumptions!$B$6),"") -> 2 | J65: =IF(F65="Monthly interest",MAX(0,Assumptions!$B$5-I65),"") | K65: =IF(F65="Bullet",G65*AD65,MAX(I65,1)*AD65) -> 11856 | L65: 46170 | M65: Medium | N65: Voice bot | O65: Early-stage delinquency: matched to risk and ticket size | P65: Call center | Q65: E - Other early delinquent | R65: Reminder + payment link | S65: Hindi | T65: Y | U65: Evening (4-8pm) | V65: Delhi | W65: Dwarka | X65: Dwarka - Town Hall | Y65: GL0517117782 | Z65: 46170 | AA65: 6 | AB65: =EDATE(Z65,AA65) -> 46354 | AC65: 18 | AD65: =ROUND(D65*AC65/100/12,0) -> 2964 | AE65: =IF(F65="Bullet",H65*AD65,MIN(MAX(I65,1),Assumptions!$B$6)*AD65) -> 5928 | AF65: =IF(F65="Bullet",MAX(0,Assumptions!$B$4-AB65),MAX(0,Assumptions!$B$4-L65)) -> 0 | AH65: =IF(AG65="","",Assumptions!$B$4-AG65) | AI65: NA | AK65: 1 | AL65: 709 | AM65: 1 | AN65: N | AO65: 78.2 | AP65: 32 | AQ65: 46279 | AR65: WhatsApp reminder | AS65: Not reachable
A66: MFLC1000065 | B66: Lakshmi Babu | C66: 9442396523 | D66: 49300 | E66: Gold loan | F66: Bullet | G66: 6 | H66: =IF(F66="Bullet",MIN(G66,Assumptions!$B$6),"") -> 2 | J66: =IF(F66="Monthly interest",MAX(0,Assumptions!$B$5-I66),"") | K66: =IF(F66="Bullet",G66*AD66,MAX(I66,1)*AD66) -> 3450 | L66: 46115 | M66: High | N66: Bot + call center | O66: High-risk accrued bullet: bot negotiates, call center follows up | P66: Field visit | Q66: C - Accrued bullet | R66: Negotiate minimum amount due | S66: Telugu | T66: Y | U66: Evening (4-8pm) | V66: Telangana | W66: Hyderabad | X66: Hyderabad - Temple Street | Y66: GL3734827283 | Z66: 46115 | AA66: 6 | AB66: =EDATE(Z66,AA66) -> 46298 | AC66: 14 | AD66: =ROUND(D66*AC66/100/12,0) -> 575 | AE66: =IF(F66="Bullet",H66*AD66,MIN(MAX(I66,1),Assumptions!$B$6)*AD66) -> 1150 | AF66: =IF(F66="Bullet",MAX(0,Assumptions!$B$4-AB66),MAX(0,Assumptions!$B$4-L66)) -> 0 | AH66: =IF(AG66="","",Assumptions!$B$4-AG66) | AI66: NA | AK66: 3 | AL66: 690 | AM66: 1 | AN66: N | AO66: 66.9 | AP66: 58 | AQ66: 46288 | AR66: Voice bot | AS66: Promised to pay
A67: MFLC1000066 | B67: Suresh Menon | C67: 9501127166 | D67: 791800 | E67: Gold loan | F67: Monthly interest | H67: =IF(F67="Bullet",MIN(G67,Assumptions!$B$6),"") | I67: 1 | J67: =IF(F67="Monthly interest",MAX(0,Assumptions!$B$5-I67),"") -> 2 | K67: =IF(F67="Bullet",G67*AD67,MAX(I67,1)*AD67) -> 9238 | L67: 46283 | M67: High | N67: Bot + call center | O67: Bouncing EII, high risk and high POS: bot first, call center for non-responders | P67: Field visit | Q67: D - Bouncing EII | R67: Reminder + part-payment negotiation, call center follow-up | S67: Malayalam | T67: Y | U67: Morning (9am-12pm) | V67: Kerala | W67: Thrissur | X67: Thrissur - Main Road | Y67: GL8691946355 | Z67: 46009 | AA67: 12 | AB67: =EDATE(Z67,AA67) -> 46374 | AC67: 14 | AD67: =ROUND(D67*AC67/100/12,0) -> 9238 | AE67: =IF(F67="Bullet",H67*AD67,MIN(MAX(I67,1),Assumptions!$B$6)*AD67) -> 9238 | AF67: =IF(F67="Bullet",MAX(0,Assumptions!$B$4-AB67),MAX(0,Assumptions!$B$4-L67)) -> 15 | AG67: 46256 | AH67: =IF(AG67="","",Assumptions!$B$4-AG67) -> 42 | AI67: N | AJ67: 2 | AK67: 0 | AL67: 650 | AM67: 4 | AN67: Y | AO67: 68.4 | AP67: 56 | AQ67: 46295 | AR67: WhatsApp reminder | AS67: No response
A68: MFLC1000067 | B68: Pooja Chauhan | C68: 9033150301 | D68: 64500 | E68: Gold loan | F68: Bullet | G68: 5 | H68: =IF(F68="Bullet",MIN(G68,Assumptions!$B$6),"") -> 2 | J68: =IF(F68="Monthly interest",MAX(0,Assumptions!$B$5-I68),"") | K68: =IF(F68="Bullet",G68*AD68,MAX(I68,1)*AD68) -> 4030 | L68: 46133 | M68: High | N68: Bot + call center | O68: High-risk accrued bullet: bot negotiates, call center follows up | P68: Field visit | Q68: C - Accrued bullet | R68: Negotiate minimum amount due | S68: Hindi | T68: Y | U68: Morning (9am-12pm) | V68: Madhya Pradesh | W68: Bhopal | X68: Bhopal - Gandhi Nagar | Y68: GL2848821367 | Z68: 46133 | AA68: 12 | AB68: =EDATE(Z68,AA68) -> 46498 | AC68: 15 | AD68: =ROUND(D68*AC68/100/12,0) -> 806 | AE68: =IF(F68="Bullet",H68*AD68,MIN(MAX(I68,1),Assumptions!$B$6)*AD68) -> 1612 | AF68: =IF(F68="Bullet",MAX(0,Assumptions!$B$4-AB68),MAX(0,Assumptions!$B$4-L68)) -> 0 | AH68: =IF(AG68="","",Assumptions!$B$4-AG68) | AI68: NA | AK68: 1 | AL68: 651 | AM68: 1 | AN68: Y | AO68: 72.7 | AP68: 54 | AQ68: 46281 | AR68: WhatsApp reminder | AS68: Promised to pay
A69: MFLC1000068 | B69: Geetha Acharya | C69: 9876530849 | D69: 102800 | E69: Gold loan | F69: Bullet | G69: 3 | H69: =IF(F69="Bullet",MIN(G69,Assumptions!$B$6),"") -> 2 | J69: =IF(F69="Monthly interest",MAX(0,Assumptions!$B$5-I69),"") | K69: =IF(F69="Bullet",G69*AD69,MAX(I69,1)*AD69) -> 3855 | L69: 46193 | M69: Medium | N69: Call center | O69: Escalated: customer refused/disputed, needs a human | P69: Field visit | Q69: E - Other early delinquent | R69: Reminder + payment link | S69: Kannada | T69: Y | U69: Evening (4-8pm) | V69: Karnataka | W69: Belagavi | X69: Belagavi - Nehru Nagar | Y69: GL9384479582 | Z69: 46193 | AA69: 6 | AB69: =EDATE(Z69,AA69) -> 46376 | AC69: 15 | AD69: =ROUND(D69*AC69/100/12,0) -> 1285 | AE69: =IF(F69="Bullet",H69*AD69,MIN(MAX(I69,1),Assumptions!$B$6)*AD69) -> 2570 | AF69: =IF(F69="Bullet",MAX(0,Assumptions!$B$4-AB69),MAX(0,Assumptions!$B$4-L69)) -> 0 | AH69: =IF(AG69="","",Assumptions!$B$4-AG69) | AI69: NA | AK69: 2 | AL69: NA | AM69: 1 | AN69: N | AO69: 78.1 | AP69: 42 | AQ69: 46280 | AR69: Voice bot | AS69: Refused / disputed
A70: MFLC1000069 | B70: Kavitha Varma | C70: 8121471764 | D70: 29000 | E70: Gold loan | F70: Bullet | G70: 3 | H70: =IF(F70="Bullet",MIN(G70,Assumptions!$B$6),"") -> 2 | J70: =IF(F70="Monthly interest",MAX(0,Assumptions!$B$5-I70),"") | K70: =IF(F70="Bullet",G70*AD70,MAX(I70,1)*AD70) -> 1089 | L70: 46202 | M70: Medium | N70: Voice bot | O70: Small ticket: bot-only, human cost not justified | P70: None - bot retry cadence | Q70: B - Small-ticket | R70: Standard reminder (no human follow-up) | S70: Telugu | T70: Y | U70: Evening (4-8pm) | V70: Telangana | W70: Hyderabad | X70: Hyderabad - Main Road | Y70: GL8204061195 | Z70: 46202 | AA70: 6 | AB70: =EDATE(Z70,AA70) -> 46385 | AC70: 15 | AD70: =ROUND(D70*AC70/100/12,0) -> 363 | AE70: =IF(F70="Bullet",H70*AD70,MIN(MAX(I70,1),Assumptions!$B$6)*AD70) -> 726 | AF70: =IF(F70="Bullet",MAX(0,Assumptions!$B$4-AB70),MAX(0,Assumptions!$B$4-L70)) -> 0 | AH70: =IF(AG70="","",Assumptions!$B$4-AG70) | AI70: NA | AK70: 1 | AL70: 627 | AM70: 0 | AN70: N | AO70: 64.1 | AP70: 33 | AQ70: 46289 | AR70: Voice bot | AS70: No response
A71: MFLC1000070 | B71: Ganesh Ravi | C71: 9319874356 | D71: 60600 | E71: Gold loan | F71: Monthly interest | H71: =IF(F71="Bullet",MIN(G71,Assumptions!$B$6),"") | I71: 1 | J71: =IF(F71="Monthly interest",MAX(0,Assumptions!$B$5-I71),"") -> 2 | K71: =IF(F71="Bullet",G71*AD71,MAX(I71,1)*AD71) -> 758 | L71: 46287 | M71: Low | N71: WhatsApp reminder | O71: Slipped regular payer: gentle digital nudge | P71: Voice bot | Q71: A - Regular monthly payer | R71: Gentle reminder + eNACH nudge | S71: Tamil | T71: Y | U71: Evening (4-8pm) | V71: Tamil Nadu | W71: Coimbatore | X71: Coimbatore - Civil Lines | Y71: GL2773852144 | Z71: 46195 | AA71: 24 | AB71: =EDATE(Z71,AA71) -> 46926 | AC71: 15 | AD71: =ROUND(D71*AC71/100/12,0) -> 758 | AE71: =IF(F71="Bullet",H71*AD71,MIN(MAX(I71,1),Assumptions!$B$6)*AD71) -> 758 | AF71: =IF(F71="Bullet",MAX(0,Assumptions!$B$4-AB71),MAX(0,Assumptions!$B$4-L71)) -> 11 | AG71: 46256 | AH71: =IF(AG71="","",Assumptions!$B$4-AG71) -> 42 | AI71: Y | AJ71: 2 | AK71: 1 | AL71: 774 | AM71: 0 | AN71: N | AO71: 49.4 | AP71: 24 | AQ71: 46297 | AR71: Voice bot | AS71: No response
A72: MFLC1000071 | B72: Lakshmi Bhat | C72: 7298795114 | D72: 146000 | E72: Gold loan | F72: Monthly interest | H72: =IF(F72="Bullet",MIN(G72,Assumptions!$B$6),"") | I72: 2 | J72: =IF(F72="Monthly interest",MAX(0,Assumptions!$B$5-I72),"") -> 1 | K72: =IF(F72="Bullet",G72*AD72,MAX(I72,1)*AD72) -> 4380 | L72: 46262 | M72: High | N72: Bot + call center | O72: Bouncing EII, high risk and high POS: bot first, call center for non-responders | P72: Field visit | Q72: D - Bouncing EII | R72: Reminder + part-payment negotiation, call center follow-up | S72: Kannada | T72: Y | U72: Morning (9am-12pm) | V72: Karnataka | W72: Mangaluru | X72: Mangaluru - Church Road | Y72: GL4412934766 | Z72: 46019 | AA72: 12 | AB72: =EDATE(Z72,AA72) -> 46384 | AC72: 18 | AD72: =ROUND(D72*AC72/100/12,0) -> 2190 | AE72: =IF(F72="Bullet",H72*AD72,MIN(MAX(I72,1),Assumptions!$B$6)*AD72) -> 4380 | AF72: =IF(F72="Bullet",MAX(0,Assumptions!$B$4-AB72),MAX(0,Assumptions!$B$4-L72)) -> 36 | AG72: 46231 | AH72: =IF(AG72="","",Assumptions!$B$4-AG72) -> 67 | AI72: N | AJ72: 2 | AK72: 0 | AL72: 595 | AM72: 3 | AN72: N | AO72: 68.9 | AP72: 57 | AQ72: 46287 | AR72: WhatsApp reminder | AS72: Needs more time
A73: MFLC1000072 | B73: Madhavi Setty | C73: 7615454252 | D73: 239500 | E73: Gold loan | F73: Bullet | G73: 5 | H73: =IF(F73="Bullet",MIN(G73,Assumptions!$B$6),"") -> 2 | J73: =IF(F73="Monthly interest",MAX(0,Assumptions!$B$5-I73),"") | K73: =IF(F73="Bullet",G73*AD73,MAX(I73,1)*AD73) -> 14970 | L73: 46140 | M73: High | N73: Bot + call center | O73: High-risk accrued bullet: bot negotiates, call center follows up | P73: Field visit | Q73: C - Accrued bullet | R73: Negotiate minimum amount due | S73: English | T73: Y | U73: Morning (9am-12pm) | V73: Telangana | W73: Warangal | X73: Warangal - MG Road | Y73: GL0740703937 | Z73: 46140 | AA73: 6 | AB73: =EDATE(Z73,AA73) -> 46323 | AC73: 15 | AD73: =ROUND(D73*AC73/100/12,0) -> 2994 | AE73: =IF(F73="Bullet",H73*AD73,MIN(MAX(I73,1),Assumptions!$B$6)*AD73) -> 5988 | AF73: =IF(F73="Bullet",MAX(0,Assumptions!$B$4-AB73),MAX(0,Assumptions!$B$4-L73)) -> 0 | AH73: =IF(AG73="","",Assumptions!$B$4-AG73) | AI73: NA | AK73: 2 | AL73: NA | AM73: 1 | AN73: N | AO73: 78.4 | AP73: 62 | AQ73: 46287 | AR73: WhatsApp reminder | AS73: Part payment made
A74: MFLC1000073 | B74: Anjaneyulu Reddy | C74: 8713012914 | D74: 234500 | E74: Gold loan | F74: Bullet | G74: 4 | H74: =IF(F74="Bullet",MIN(G74,Assumptions!$B$6),"") -> 2 | J74: =IF(F74="Monthly interest",MAX(0,Assumptions!$B$5-I74),"") | K74: =IF(F74="Bullet",G74*AD74,MAX(I74,1)*AD74) -> 9380 | L74: 46153 | M74: Medium | N74: Call center | O74: Early-stage delinquency: matched to risk and ticket size | P74: Field visit | Q74: E - Other early delinquent | R74: Reminder + payment link | S74: English | T74: Y | U74: Afternoon (12-4pm) | V74: Andhra Pradesh | W74: Nellore | X74: Nellore - Civil Lines | Y74: GL6180226851 | Z74: 46153 | AA74: 6 | AB74: =EDATE(Z74,AA74) -> 46337 | AC74: 12 | AD74: =ROUND(D74*AC74/100/12,0) -> 2345 | AE74: =IF(F74="Bullet",H74*AD74,MIN(MAX(I74,1),Assumptions!$B$6)*AD74) -> 4690 | AF74: =IF(F74="Bullet",MAX(0,Assumptions!$B$4-AB74),MAX(0,Assumptions!$B$4-L74)) -> 0 | AH74: =IF(AG74="","",Assumptions!$B$4-AG74) | AI74: NA | AK74: 1 | AL74: 672 | AM74: 1 | AN74: N | AO74: 64 | AP74: 33 | AQ74: 46282 | AR74: Voice bot | AS74: Not reachable
A75: MFLC1000074 | B75: Remya Thomas | C75: 9313610414 | D75: 66200 | E75: Gold loan | F75: Bullet | G75: 3 | H75: =IF(F75="Bullet",MIN(G75,Assumptions!$B$6),"") -> 2 | J75: =IF(F75="Monthly interest",MAX(0,Assumptions!$B$5-I75),"") | K75: =IF(F75="Bullet",G75*AD75,MAX(I75,1)*AD75) -> 2316 | L75: 46200 | M75: Medium | N75: Voice bot | O75: Early-stage delinquency: matched to risk and ticket size | P75: Call center | Q75: E - Other early delinquent | R75: Reminder + payment link | S75: Malayalam | T75: Y | U75: Afternoon (12-4pm) | V75: Kerala | W75: Kannur | X75: Kannur - Bus Stand | Y75: GL7522943381 | Z75: 46200 | AA75: 12 | AB75: =EDATE(Z75,AA75) -> 46565 | AC75: 14 | AD75: =ROUND(D75*AC75/100/12,0) -> 772 | AE75: =IF(F75="Bullet",H75*AD75,MIN(MAX(I75,1),Assumptions!$B$6)*AD75) -> 1544 | AF75: =IF(F75="Bullet",MAX(0,Assumptions!$B$4-AB75),MAX(0,Assumptions!$B$4-L75)) -> 0 | AH75: =IF(AG75="","",Assumptions!$B$4-AG75) | AI75: NA | AK75: 0 | AL75: 737 | AM75: 2 | AN75: Y | AO75: 80.4 | AP75: 40 | AS75: No prior contact
A76: MFLC1000075 | B76: Santhosh Kumar | C76: 7362424264 | D76: 37100 | E76: Gold loan | F76: Monthly interest | H76: =IF(F76="Bullet",MIN(G76,Assumptions!$B$6),"") | I76: 2 | J76: =IF(F76="Monthly interest",MAX(0,Assumptions!$B$5-I76),"") -> 1 | K76: =IF(F76="Bullet",G76*AD76,MAX(I76,1)*AD76) -> 928 | L76: 46243 | M76: Medium | N76: Voice bot | O76: Small ticket: bot-only, human cost not justified | P76: None - bot retry cadence | Q76: B - Small-ticket | R76: Standard reminder (no human follow-up) | S76: Malayalam | T76: Y | U76: Morning (9am-12pm) | V76: Kerala | W76: Kozhikode | X76: Kozhikode - MG Road | Y76: GL4563975560 | Z76: 46000 | AA76: 12 | AB76: =EDATE(Z76,AA76) -> 46365 | AC76: 15 | AD76: =ROUND(D76*AC76/100/12,0) -> 464 | AE76: =IF(F76="Bullet",H76*AD76,MIN(MAX(I76,1),Assumptions!$B$6)*AD76) -> 928 | AF76: =IF(F76="Bullet",MAX(0,Assumptions!$B$4-AB76),MAX(0,Assumptions!$B$4-L76)) -> 55 | AG76: 46214 | AH76: =IF(AG76="","",Assumptions!$B$4-AG76) -> 84 | AI76: N | AJ76: 2 | AK76: 2 | AL76: 781 | AM76: 0 | AN76: N | AO76: 68.1 | AP76: 42 | AQ76: 46289 | AR76: Call center | AS76: Promised to pay
A77: MFLC1000076 | B77: Venkatesh Hegde | C77: 8660537058 | D77: 35800 | E77: Gold loan | F77: Bullet | G77: 1 | H77: =IF(F77="Bullet",MIN(G77,Assumptions!$B$6),"") -> 1 | J77: =IF(F77="Monthly interest",MAX(0,Assumptions!$B$5-I77),"") | K77: =IF(F77="Bullet",G77*AD77,MAX(I77,1)*AD77) -> 448 | L77: 46245 | M77: Low | N77: Voice bot | O77: Escalated: no response on whatsapp reminder | P77: None - bot retry cadence | Q77: B - Small-ticket | R77: Standard reminder (no human follow-up) | S77: Kannada | T77: Y | U77: Afternoon (12-4pm) | V77: Karnataka | W77: Mangaluru | X77: Mangaluru - Station Road | Y77: GL9786950624 | Z77: 46245 | AA77: 6 | AB77: =EDATE(Z77,AA77) -> 46429 | AC77: 15 | AD77: =ROUND(D77*AC77/100/12,0) -> 448 | AE77: =IF(F77="Bullet",H77*AD77,MIN(MAX(I77,1),Assumptions!$B$6)*AD77) -> 448 | AF77: =IF(F77="Bullet",MAX(0,Assumptions!$B$4-AB77),MAX(0,Assumptions!$B$4-L77)) -> 0 | AH77: =IF(AG77="","",Assumptions!$B$4-AG77) | AI77: NA | AK77: 0 | AL77: 666 | AM77: 0 | AN77: N | AO77: 76.6 | AP77: 25 | AQ77: 46281 | AR77: WhatsApp reminder | AS77: No response
A78: MFLC1000077 | B78: Anil Kumar | C78: 9580843756 | D78: 214400 | E78: Gold loan | F78: Monthly interest | H78: =IF(F78="Bullet",MIN(G78,Assumptions!$B$6),"") | I78: 1 | J78: =IF(F78="Monthly interest",MAX(0,Assumptions!$B$5-I78),"") -> 2 | K78: =IF(F78="Bullet",G78*AD78,MAX(I78,1)*AD78) -> 4288 | L78: 46288 | M78: Low | N78: WhatsApp reminder | O78: Slipped regular payer: gentle digital nudge | P78: Voice bot | Q78: A - Regular monthly payer | R78: Gentle reminder + eNACH nudge | S78: Malayalam | T78: Y | U78: Evening (4-8pm) | V78: Kerala | W78: Kollam | X78: Kollam - Nehru Nagar | Y78: GL5332843181 | Z78: 46045 | AA78: 12 | AB78: =EDATE(Z78,AA78) -> 46410 | AC78: 24 | AD78: =ROUND(D78*AC78/100/12,0) -> 4288 | AE78: =IF(F78="Bullet",H78*AD78,MIN(MAX(I78,1),Assumptions!$B$6)*AD78) -> 4288 | AF78: =IF(F78="Bullet",MAX(0,Assumptions!$B$4-AB78),MAX(0,Assumptions!$B$4-L78)) -> 10 | AG78: 46258 | AH78: =IF(AG78="","",Assumptions!$B$4-AG78) -> 40 | AI78: N | AJ78: 1 | AK78: 0 | AL78: 702 | AM78: 1 | AN78: N | AO78: 66.8 | AP78: 21 | AQ78: 46295 | AR78: WhatsApp reminder | AS78: Promised to pay
A79: MFLC1000078 | B79: Latha Menon | C79: 7340848261 | D79: 251500 | E79: Gold loan | F79: Bullet | G79: 1 | H79: =IF(F79="Bullet",MIN(G79,Assumptions!$B$6),"") -> 1 | J79: =IF(F79="Monthly interest",MAX(0,Assumptions!$B$5-I79),"") | K79: =IF(F79="Bullet",G79*AD79,MAX(I79,1)*AD79) -> 2725 | L79: 46260 | M79: Low | N79: WhatsApp reminder | O79: Early-stage delinquency: matched to risk and ticket size | P79: Voice bot | Q79: E - Other early delinquent | R79: Reminder + payment link | S79: Malayalam | T79: Y | U79: Evening (4-8pm) | V79: Kerala | W79: Kollam | X79: Kollam - MG Road | Y79: GL0244932708 | Z79: 46260 | AA79: 12 | AB79: =EDATE(Z79,AA79) -> 46625 | AC79: 13 | AD79: =ROUND(D79*AC79/100/12,0) -> 2725 | AE79: =IF(F79="Bullet",H79*AD79,MIN(MAX(I79,1),Assumptions!$B$6)*AD79) -> 2725 | AF79: =IF(F79="Bullet",MAX(0,Assumptions!$B$4-AB79),MAX(0,Assumptions!$B$4-L79)) -> 0 | AH79: =IF(AG79="","",Assumptions!$B$4-AG79) | AI79: NA | AK79: 0 | AL79: 702 | AM79: 4 | AN79: N | AO79: 77.1 | AP79: 14 | AS79: No prior contact
A80: MFLC1000079 | B80: Savitha Reddy | C80: 9750837848 | D80: 70100 | E80: Gold loan | F80: Monthly interest | H80: =IF(F80="Bullet",MIN(G80,Assumptions!$B$6),"") | I80: 2 | J80: =IF(F80="Monthly interest",MAX(0,Assumptions!$B$5-I80),"") -> 1 | K80: =IF(F80="Bullet",G80*AD80,MAX(I80,1)*AD80) -> 1870 | L80: 46266 | M80: Medium | N80: Call center | O80: Escalated: no response on voice bot | P80: Field visit | Q80: E - Other early delinquent | R80: Reminder + payment link | S80: Kannada | T80: N | U80: Morning (9am-12pm) | V80: Karnataka | W80: Belagavi | X80: Belagavi - Temple Street | Y80: GL3318373315 | Z80: 46174 | AA80: 12 | AB80: =EDATE(Z80,AA80) -> 46539 | AC80: 16 | AD80: =ROUND(D80*AC80/100/12,0) -> 935 | AE80: =IF(F80="Bullet",H80*AD80,MIN(MAX(I80,1),Assumptions!$B$6)*AD80) -> 1870 | AF80: =IF(F80="Bullet",MAX(0,Assumptions!$B$4-AB80),MAX(0,Assumptions!$B$4-L80)) -> 32 | AG80: 46239 | AH80: =IF(AG80="","",Assumptions!$B$4-AG80) -> 59 | AI80: N | AJ80: 2 | AK80: 1 | AL80: 671 | AM80: 1 | AN80: N | AO80: 56.1 | AP80: 46 | AQ80: 46275 | AR80: Voice bot | AS80: No response
A81: MFLC1000080 | B81: Swathi Sastry | C81: 7437915161 | D81: 63800 | E81: Gold loan | F81: Monthly interest | H81: =IF(F81="Bullet",MIN(G81,Assumptions!$B$6),"") | I81: 1 | J81: =IF(F81="Monthly interest",MAX(0,Assumptions!$B$5-I81),"") -> 2 | K81: =IF(F81="Bullet",G81*AD81,MAX(I81,1)*AD81) -> 851 | L81: 46285 | M81: Low | N81: Voice bot | O81: Escalated: no response on whatsapp reminder | P81: WhatsApp reminder | Q81: A - Regular monthly payer | R81: Gentle reminder + eNACH nudge | S81: Telugu | T81: Y | U81: Afternoon (12-4pm) | V81: Telangana | W81: Nizamabad | X81: Nizamabad - Gandhi Nagar | Y81: GL3962243991 | Z81: 46073 | AA81: 18 | AB81: =EDATE(Z81,AA81) -> 46619 | AC81: 16 | AD81: =ROUND(D81*AC81/100/12,0) -> 851 | AE81: =IF(F81="Bullet",H81*AD81,MIN(MAX(I81,1),Assumptions!$B$6)*AD81) -> 851 | AF81: =IF(F81="Bullet",MAX(0,Assumptions!$B$4-AB81),MAX(0,Assumptions!$B$4-L81)) -> 13 | AG81: 46254 | AH81: =IF(AG81="","",Assumptions!$B$4-AG81) -> 44 | AI81: N | AJ81: 2 | AK81: 0 | AL81: 782 | AM81: 0 | AN81: N | AO81: 57.9 | AP81: 19 | AQ81: 46283 | AR81: WhatsApp reminder | AS81: No response
A82: MFLC1000081 | B82: Manjula Reddy | C82: 6780234303 | D82: 1391400 | E82: Gold loan | F82: Monthly interest | H82: =IF(F82="Bullet",MIN(G82,Assumptions!$B$6),"") | I82: 1 | J82: =IF(F82="Monthly interest",MAX(0,Assumptions!$B$5-I82),"") -> 2 | K82: =IF(F82="Bullet",G82*AD82,MAX(I82,1)*AD82) -> 27828 | L82: 46298 | M82: Medium | N82: Voice bot | O82: No WhatsApp opt-in: routed to voice bot | P82: Call center | Q82: A - Regular monthly payer | R82: Gentle reminder + eNACH nudge | S82: Kannada | T82: N | U82: Evening (4-8pm) | V82: Karnataka | W82: Belagavi | X82: Belagavi - Town Hall | Y82: GL8436727313 | Z82: 46237 | AA82: 12 | AB82: =EDATE(Z82,AA82) -> 46602 | AC82: 24 | AD82: =ROUND(D82*AC82/100/12,0) -> 27828 | AE82: =IF(F82="Bullet",H82*AD82,MIN(MAX(I82,1),Assumptions!$B$6)*AD82) -> 27828 | AF82: =IF(F82="Bullet",MAX(0,Assumptions!$B$4-AB82),MAX(0,Assumptions!$B$4-L82)) -> 0 | AG82: 46272 | AH82: =IF(AG82="","",Assumptions!$B$4-AG82) -> 26 | AI82: N | AJ82: 2 | AK82: 0 | AL82: 646 | AM82: 1 | AN82: Y | AO82: 76.4 | AP82: 42 | AQ82: 46293 | AR82: WhatsApp reminder | AS82: Promised to pay
A83: MFLC1000082 | B83: Prakash Murugan | C83: 9403000076 | D83: 70900 | E83: Gold loan | F83: Bullet | G83: 3 | H83: =IF(F83="Bullet",MIN(G83,Assumptions!$B$6),"") -> 2 | J83: =IF(F83="Monthly interest",MAX(0,Assumptions!$B$5-I83),"") | K83: =IF(F83="Bullet",G83*AD83,MAX(I83,1)*AD83) -> 2304 | L83: 46192 | M83: Medium | N83: Voice bot | O83: Early-stage delinquency: matched to risk and ticket size | P83: Call center | Q83: E - Other early delinquent | R83: Reminder + payment link | S83: Tamil | T83: Y | U83: Morning (9am-12pm) | V83: Tamil Nadu | W83: Chennai | X83: Chennai - Industrial Estate | Y83: GL3718766907 | Z83: 46192 | AA83: 12 | AB83: =EDATE(Z83,AA83) -> 46557 | AC83: 13 | AD83: =ROUND(D83*AC83/100/12,0) -> 768 | AE83: =IF(F83="Bullet",H83*AD83,MIN(MAX(I83,1),Assumptions!$B$6)*AD83) -> 1536 | AF83: =IF(F83="Bullet",MAX(0,Assumptions!$B$4-AB83),MAX(0,Assumptions!$B$4-L83)) -> 0 | AH83: =IF(AG83="","",Assumptions!$B$4-AG83) | AI83: NA | AK83: 2 | AL83: 626 | AM83: 1 | AN83: N | AO83: 61.8 | AP83: 44 | AQ83: 46284 | AR83: Call center | AS83: No response
A84: MFLC1000083 | B84: Rekha Jain | C84: 9789604342 | D84: 371900 | E84: Gold loan | F84: Bullet | G84: 6 | H84: =IF(F84="Bullet",MIN(G84,Assumptions!$B$6),"") -> 2 | J84: =IF(F84="Monthly interest",MAX(0,Assumptions!$B$5-I84),"") | K84: =IF(F84="Bullet",G84*AD84,MAX(I84,1)*AD84) -> 33474 | L84: 46094 | M84: High | N84: Bot + call center | O84: High-risk accrued bullet: bot negotiates, call center follows up | P84: Field visit | Q84: C - Accrued bullet | R84: Negotiate minimum amount due | S84: Hindi | T84: Y | U84: Morning (9am-12pm) | V84: Haryana | W84: Gurugram | X84: Gurugram - Civil Lines | Y84: GL3625376998 | Z84: 46094 | AA84: 6 | AB84: =EDATE(Z84,AA84) -> 46278 | AC84: 18 | AD84: =ROUND(D84*AC84/100/12,0) -> 5579 | AE84: =IF(F84="Bullet",H84*AD84,MIN(MAX(I84,1),Assumptions!$B$6)*AD84) -> 11158 | AF84: =IF(F84="Bullet",MAX(0,Assumptions!$B$4-AB84),MAX(0,Assumptions!$B$4-L84)) -> 20 | AH84: =IF(AG84="","",Assumptions!$B$4-AG84) | AI84: NA | AK84: 1 | AL84: 583 | AM84: 4 | AN84: N | AO84: 73.8 | AP84: 80 | AQ84: 46291 | AR84: Field visit | AS84: Not reachable
A85: MFLC1000084 | B85: Ramesh Naidu | C85: 9872126721 | D85: 69700 | E85: Gold loan | F85: Monthly interest | H85: =IF(F85="Bullet",MIN(G85,Assumptions!$B$6),"") | I85: 1 | J85: =IF(F85="Monthly interest",MAX(0,Assumptions!$B$5-I85),"") -> 2 | K85: =IF(F85="Bullet",G85*AD85,MAX(I85,1)*AD85) -> 1394 | L85: 46283 | M85: High | N85: Bot + call center | O85: Bouncing EII, high risk and high POS: bot first, call center for non-responders | P85: Field visit | Q85: D - Bouncing EII | R85: Reminder + part-payment negotiation, call center follow-up | S85: Telugu | T85: N | U85: Afternoon (12-4pm) | V85: Andhra Pradesh | W85: Nellore | X85: Nellore - Town Hall | Y85: GL5648174324 | Z85: 46221 | AA85: 18 | AB85: =EDATE(Z85,AA85) -> 46770 | AC85: 24 | AD85: =ROUND(D85*AC85/100/12,0) -> 1394 | AE85: =IF(F85="Bullet",H85*AD85,MIN(MAX(I85,1),Assumptions!$B$6)*AD85) -> 1394 | AF85: =IF(F85="Bullet",MAX(0,Assumptions!$B$4-AB85),MAX(0,Assumptions!$B$4-L85)) -> 15 | AG85: 46252 | AH85: =IF(AG85="","",Assumptions!$B$4-AG85) -> 46 | AI85: N | AJ85: 2 | AK85: 0 | AL85: 615 | AM85: 1 | AN85: Y | AO85: 56.7 | AP85: 51 | AQ85: 46285 | AR85: WhatsApp reminder | AS85: Promised to pay
A86: MFLC1000085 | B86: Lakshmi Venkatesh | C86: 8256872534 | D86: 271700 | E86: Gold loan | F86: Bullet | G86: 4 | H86: =IF(F86="Bullet",MIN(G86,Assumptions!$B$6),"") -> 2 | J86: =IF(F86="Monthly interest",MAX(0,Assumptions!$B$5-I86),"") | K86: =IF(F86="Bullet",G86*AD86,MAX(I86,1)*AD86) -> 16304 | L86: 46166 | M86: Low | N86: Voice bot | O86: Early-stage delinquency: matched to risk and ticket size | P86: Call center | Q86: E - Other early delinquent | R86: Reminder + payment link | S86: Tamil | T86: N | U86: Afternoon (12-4pm) | V86: Tamil Nadu | W86: Madurai | X86: Madurai - Nehru Nagar | Y86: GL7442493108 | Z86: 46166 | AA86: 12 | AB86: =EDATE(Z86,AA86) -> 46531 | AC86: 18 | AD86: =ROUND(D86*AC86/100/12,0) -> 4076 | AE86: =IF(F86="Bullet",H86*AD86,MIN(MAX(I86,1),Assumptions!$B$6)*AD86) -> 8152 | AF86: =IF(F86="Bullet",MAX(0,Assumptions!$B$4-AB86),MAX(0,Assumptions!$B$4-L86)) -> 0 | AH86: =IF(AG86="","",Assumptions!$B$4-AG86) | AI86: NA | AK86: 0 | AL86: 723 | AM86: 4 | AN86: N | AO86: 60.6 | AP86: 29 | AQ86: 46284 | AR86: Field visit | AS86: Part payment made
A87: MFLC1000086 | B87: Mahesh Naidu | C87: 9455031227 | D87: 155100 | E87: Gold loan | F87: Monthly interest | H87: =IF(F87="Bullet",MIN(G87,Assumptions!$B$6),"") | I87: 1 | J87: =IF(F87="Monthly interest",MAX(0,Assumptions!$B$5-I87),"") -> 2 | K87: =IF(F87="Bullet",G87*AD87,MAX(I87,1)*AD87) -> 2585 | L87: 46281 | M87: Medium | N87: WhatsApp reminder | O87: Slipped regular payer: gentle digital nudge | P87: Voice bot | Q87: A - Regular monthly payer | R87: Gentle reminder + eNACH nudge | S87: English | T87: Y | U87: Morning (9am-12pm) | V87: Andhra Pradesh | W87: Nellore | X87: Nellore - Church Road | Y87: GL1129485527 | Z87: 46069 | AA87: 24 | AB87: =EDATE(Z87,AA87) -> 46799 | AC87: 20 | AD87: =ROUND(D87*AC87/100/12,0) -> 2585 | AE87: =IF(F87="Bullet",H87*AD87,MIN(MAX(I87,1),Assumptions!$B$6)*AD87) -> 2585 | AF87: =IF(F87="Bullet",MAX(0,Assumptions!$B$4-AB87),MAX(0,Assumptions!$B$4-L87)) -> 17 | AG87: 46252 | AH87: =IF(AG87="","",Assumptions!$B$4-AG87) -> 46 | AI87: N | AJ87: 1 | AK87: 0 | AL87: NA | AM87: 1 | AN87: Y | AO87: 65.4 | AP87: 37 | AQ87: 46274 | AR87: Call center | AS87: Promised to pay
A88: MFLC1000087 | B88: Kumar Venkatesh | C88: 7268855332 | D88: 49300 | E88: Gold loan | F88: Monthly interest | H88: =IF(F88="Bullet",MIN(G88,Assumptions!$B$6),"") | I88: 2 | J88: =IF(F88="Monthly interest",MAX(0,Assumptions!$B$5-I88),"") -> 1 | K88: =IF(F88="Bullet",G88*AD88,MAX(I88,1)*AD88) -> 1314 | L88: 46258 | M88: High | N88: Bot + call center | O88: High risk (small ticket): bot first, call center follows up | P88: Field visit | Q88: B - Small-ticket | R88: Standard reminder (no human follow-up) | S88: Tamil | T88: Y | U88: Afternoon (12-4pm) | V88: Tamil Nadu | W88: Tirunelveli | X88: Tirunelveli - Nehru Nagar | Y88: GL0653553439 | Z88: 46136 | AA88: 12 | AB88: =EDATE(Z88,AA88) -> 46501 | AC88: 16 | AD88: =ROUND(D88*AC88/100/12,0) -> 657 | AE88: =IF(F88="Bullet",H88*AD88,MIN(MAX(I88,1),Assumptions!$B$6)*AD88) -> 1314 | AF88: =IF(F88="Bullet",MAX(0,Assumptions!$B$4-AB88),MAX(0,Assumptions!$B$4-L88)) -> 40 | AG88: 46228 | AH88: =IF(AG88="","",Assumptions!$B$4-AG88) -> 70 | AI88: N | AJ88: 2 | AK88: 3 | AL88: 686 | AM88: 1 | AN88: N | AO88: 68.1 | AP88: 57 | AQ88: 46287 | AR88: Voice bot | AS88: Refused / disputed
A89: MFLC1000088 | B89: Rani Joseph | C89: 9663078277 | D89: 105500 | E89: Gold loan | F89: Bullet | G89: 2 | H89: =IF(F89="Bullet",MIN(G89,Assumptions!$B$6),"") -> 2 | J89: =IF(F89="Monthly interest",MAX(0,Assumptions!$B$5-I89),"") | K89: =IF(F89="Bullet",G89*AD89,MAX(I89,1)*AD89) -> 2638 | L89: 46222 | M89: Medium | N89: Voice bot | O89: Early-stage delinquency: matched to risk and ticket size | P89: Call center | Q89: E - Other early delinquent | R89: Reminder + payment link | S89: Malayalam | T89: Y | U89: Evening (4-8pm) | V89: Kerala | W89: Kollam | X89: Kollam - Bus Stand | Y89: GL6433909360 | Z89: 46222 | AA89: 12 | AB89: =EDATE(Z89,AA89) -> 46587 | AC89: 15 | AD89: =ROUND(D89*AC89/100/12,0) -> 1319 | AE89: =IF(F89="Bullet",H89*AD89,MIN(MAX(I89,1),Assumptions!$B$6)*AD89) -> 2638 | AF89: =IF(F89="Bullet",MAX(0,Assumptions!$B$4-AB89),MAX(0,Assumptions!$B$4-L89)) -> 0 | AH89: =IF(AG89="","",Assumptions!$B$4-AG89) | AI89: NA | AK89: 2 | AL89: 707 | AM89: 3 | AN89: N | AO89: 80.6 | AP89: 35 | AQ89: 46286 | AR89: Voice bot | AS89: Needs more time
A90: MFLC1000089 | B90: Devi Kannan | C90: 9231850642 | D90: 17000 | E90: Gold loan | F90: Monthly interest | H90: =IF(F90="Bullet",MIN(G90,Assumptions!$B$6),"") | I90: 2 | J90: =IF(F90="Monthly interest",MAX(0,Assumptions!$B$5-I90),"") -> 1 | K90: =IF(F90="Bullet",G90*AD90,MAX(I90,1)*AD90) -> 680 | L90: 46255 | M90: High | N90: Bot + call center | O90: High risk (small ticket): bot first, call center follows up | P90: Field visit | Q90: B - Small-ticket | R90: Standard reminder (no human follow-up) | S90: Tamil | T90: Y | U90: Evening (4-8pm) | V90: Tamil Nadu | W90: Madurai | X90: Madurai - Town Hall | Y90: GL9256440389 | Z90: 46074 | AA90: 12 | AB90: =EDATE(Z90,AA90) -> 46439 | AC90: 24 | AD90: =ROUND(D90*AC90/100/12,0) -> 340 | AE90: =IF(F90="Bullet",H90*AD90,MIN(MAX(I90,1),Assumptions!$B$6)*AD90) -> 680 | AF90: =IF(F90="Bullet",MAX(0,Assumptions!$B$4-AB90),MAX(0,Assumptions!$B$4-L90)) -> 43 | AG90: 46225 | AH90: =IF(AG90="","",Assumptions!$B$4-AG90) -> 73 | AI90: Y | AJ90: 4 | AK90: 1 | AL90: NA | AM90: 2 | AN90: N | AO90: 79.5 | AP90: 62 | AS90: No prior contact
A91: MFLC1000090 | B91: Sajeev George | C91: 8718920131 | D91: 151100 | E91: Gold loan | F91: Bullet | G91: 5 | H91: =IF(F91="Bullet",MIN(G91,Assumptions!$B$6),"") -> 2 | J91: =IF(F91="Monthly interest",MAX(0,Assumptions!$B$5-I91),"") | K91: =IF(F91="Bullet",G91*AD91,MAX(I91,1)*AD91) -> 8185 | L91: 46132 | M91: High | N91: Bot + call center | O91: High-risk accrued bullet: bot negotiates, call center follows up | P91: Field visit | Q91: C - Accrued bullet | R91: Negotiate minimum amount due | S91: Malayalam | T91: Y | U91: Evening (4-8pm) | V91: Kerala | W91: Kochi | X91: Kochi - Market Road | Y91: GL0106397512 | Z91: 46132 | AA91: 6 | AB91: =EDATE(Z91,AA91) -> 46315 | AC91: 13 | AD91: =ROUND(D91*AC91/100/12,0) -> 1637 | AE91: =IF(F91="Bullet",H91*AD91,MIN(MAX(I91,1),Assumptions!$B$6)*AD91) -> 3274 | AF91: =IF(F91="Bullet",MAX(0,Assumptions!$B$4-AB91),MAX(0,Assumptions!$B$4-L91)) -> 0 | AH91: =IF(AG91="","",Assumptions!$B$4-AG91) | AI91: NA | AK91: 1 | AL91: 671 | AM91: 1 | AN91: N | AO91: 65.5 | AP91: 49 | AQ91: 46274 | AR91: Voice bot | AS91: Promised to pay
A92: MFLC1000091 | B92: Seema Kumar | C92: 9893008300 | D92: 125900 | E92: Gold loan | F92: Monthly interest | H92: =IF(F92="Bullet",MIN(G92,Assumptions!$B$6),"") | I92: 1 | J92: =IF(F92="Monthly interest",MAX(0,Assumptions!$B$5-I92),"") -> 2 | K92: =IF(F92="Bullet",G92*AD92,MAX(I92,1)*AD92) -> 1574 | L92: 46288 | M92: Medium | N92: WhatsApp reminder | O92: Slipped regular payer: gentle digital nudge | P92: Voice bot | Q92: A - Regular monthly payer | R92: Gentle reminder + eNACH nudge | S92: Hindi | T92: Y | U92: Evening (4-8pm) | V92: Madhya Pradesh | W92: Gwalior | X92: Gwalior - Bus Stand | Y92: GL7420967672 | Z92: 46196 | AA92: 12 | AB92: =EDATE(Z92,AA92) -> 46561 | AC92: 15 | AD92: =ROUND(D92*AC92/100/12,0) -> 1574 | AE92: =IF(F92="Bullet",H92*AD92,MIN(MAX(I92,1),Assumptions!$B$6)*AD92) -> 1574 | AF92: =IF(F92="Bullet",MAX(0,Assumptions!$B$4-AB92),MAX(0,Assumptions!$B$4-L92)) -> 10 | AG92: 46258 | AH92: =IF(AG92="","",Assumptions!$B$4-AG92) -> 40 | AI92: N | AJ92: 1 | AK92: 0 | AL92: 731 | AM92: 1 | AN92: Y | AO92: 61.1 | AP92: 31 | AS92: No prior contact
A93: MFLC1000092 | B93: Venkatesh Shetty | C93: 6001263611 | D93: 427700 | E93: Gold loan | F93: Bullet | G93: 5 | H93: =IF(F93="Bullet",MIN(G93,Assumptions!$B$6),"") -> 2 | J93: =IF(F93="Monthly interest",MAX(0,Assumptions!$B$5-I93),"") | K93: =IF(F93="Bullet",G93*AD93,MAX(I93,1)*AD93) -> 24950 | L93: 46140 | M93: High | N93: Bot + call center | O93: High-risk accrued bullet: bot negotiates, call center follows up | P93: Field visit | Q93: C - Accrued bullet | R93: Negotiate minimum amount due | S93: Kannada | T93: Y | U93: Morning (9am-12pm) | V93: Karnataka | W93: Hubballi | X93: Hubballi - Civil Lines | Y93: GL6095694164 | Z93: 46140 | AA93: 6 | AB93: =EDATE(Z93,AA93) -> 46323 | AC93: 14 | AD93: =ROUND(D93*AC93/100/12,0) -> 4990 | AE93: =IF(F93="Bullet",H93*AD93,MIN(MAX(I93,1),Assumptions!$B$6)*AD93) -> 9980 | AF93: =IF(F93="Bullet",MAX(0,Assumptions!$B$4-AB93),MAX(0,Assumptions!$B$4-L93)) -> 0 | AH93: =IF(AG93="","",Assumptions!$B$4-AG93) | AI93: NA | AK93: 1 | AL93: 699 | AM93: 1 | AN93: N | AO93: 77.9 | AP93: 51 | AQ93: 46293 | AR93: Call center | AS93: Refused / disputed
A94: MFLC1000093 | B94: Anitha Varghese | C94: 8419019238 | D94: 104900 | E94: Gold loan | F94: Monthly interest | H94: =IF(F94="Bullet",MIN(G94,Assumptions!$B$6),"") | I94: 2 | J94: =IF(F94="Monthly interest",MAX(0,Assumptions!$B$5-I94),"") -> 1 | K94: =IF(F94="Bullet",G94*AD94,MAX(I94,1)*AD94) -> 4196 | L94: 46247 | M94: High | N94: Bot + call center | O94: Bouncing EII, high risk and high POS: bot first, call center for non-responders | P94: Field visit | Q94: D - Bouncing EII | R94: Reminder + part-payment negotiation, call center follow-up | S94: Malayalam | T94: Y | U94: Morning (9am-12pm) | V94: Kerala | W94: Kottayam | X94: Kottayam - MG Road | Y94: GL7412188851 | Z94: 46004 | AA94: 12 | AB94: =EDATE(Z94,AA94) -> 46369 | AC94: 24 | AD94: =ROUND(D94*AC94/100/12,0) -> 2098 | AE94: =IF(F94="Bullet",H94*AD94,MIN(MAX(I94,1),Assumptions!$B$6)*AD94) -> 4196 | AF94: =IF(F94="Bullet",MAX(0,Assumptions!$B$4-AB94),MAX(0,Assumptions!$B$4-L94)) -> 51 | AG94: 46217 | AH94: =IF(AG94="","",Assumptions!$B$4-AG94) -> 81 | AI94: N | AJ94: 2 | AK94: 0 | AL94: 619 | AM94: 2 | AN94: N | AO94: 53.6 | AP94: 56 | AQ94: 46285 | AR94: WhatsApp reminder | AS94: Refused / disputed
A95: MFLC1000094 | B95: Fathima Mohammed | C95: 9654509322 | D95: 57600 | E95: Gold loan | F95: Monthly interest | H95: =IF(F95="Bullet",MIN(G95,Assumptions!$B$6),"") | I95: 1 | J95: =IF(F95="Monthly interest",MAX(0,Assumptions!$B$5-I95),"") -> 2 | K95: =IF(F95="Bullet",G95*AD95,MAX(I95,1)*AD95) -> 864 | L95: 46282 | M95: Medium | N95: WhatsApp reminder | O95: Slipped regular payer: gentle digital nudge | P95: Voice bot | Q95: A - Regular monthly payer | R95: Gentle reminder + eNACH nudge | S95: Malayalam | T95: Y | U95: Morning (9am-12pm) | V95: Kerala | W95: Alappuzha | X95: Alappuzha - Gandhi Nagar | Y95: GL8545337980 | Z95: 46070 | AA95: 12 | AB95: =EDATE(Z95,AA95) -> 46435 | AC95: 18 | AD95: =ROUND(D95*AC95/100/12,0) -> 864 | AE95: =IF(F95="Bullet",H95*AD95,MIN(MAX(I95,1),Assumptions!$B$6)*AD95) -> 864 | AF95: =IF(F95="Bullet",MAX(0,Assumptions!$B$4-AB95),MAX(0,Assumptions!$B$4-L95)) -> 16 | AG95: 46256 | AH95: =IF(AG95="","",Assumptions!$B$4-AG95) -> 42 | AI95: Y | AJ95: 3 | AK95: 0 | AL95: 700 | AM95: 1 | AN95: Y | AO95: 67.8 | AP95: 37 | AQ95: 46296 | AR95: Call center | AS95: Needs more time
A96: MFLC1000095 | B96: Savitha Rao | C96: 7529280327 | D96: 351400 | E96: Gold loan | F96: Bullet | G96: 6 | H96: =IF(F96="Bullet",MIN(G96,Assumptions!$B$6),"") -> 2 | J96: =IF(F96="Monthly interest",MAX(0,Assumptions!$B$5-I96),"") | K96: =IF(F96="Bullet",G96*AD96,MAX(I96,1)*AD96) -> 24600 | L96: 46101 | M96: Medium | N96: Voice bot | O96: Accrued bullet: bot negotiates minimum amount due | P96: Call center | Q96: C - Accrued bullet | R96: Negotiate minimum amount due | S96: Kannada | T96: Y | U96: Evening (4-8pm) | V96: Karnataka | W96: Mangaluru | X96: Mangaluru - Bus Stand | Y96: GL2331405540 | Z96: 46101 | AA96: 12 | AB96: =EDATE(Z96,AA96) -> 46466 | AC96: 14 | AD96: =ROUND(D96*AC96/100/12,0) -> 4100 | AE96: =IF(F96="Bullet",H96*AD96,MIN(MAX(I96,1),Assumptions!$B$6)*AD96) -> 8200 | AF96: =IF(F96="Bullet",MAX(0,Assumptions!$B$4-AB96),MAX(0,Assumptions!$B$4-L96)) -> 0 | AH96: =IF(AG96="","",Assumptions!$B$4-AG96) | AI96: NA | AK96: 2 | AL96: 736 | AM96: 1 | AN96: N | AO96: 76.8 | AP96: 47 | AQ96: 46282 | AR96: Call center | AS96: No response
A97: MFLC1000096 | B97: Kavitha Venkatesh | C97: 8749064919 | D97: 137600 | E97: Gold loan | F97: Monthly interest | H97: =IF(F97="Bullet",MIN(G97,Assumptions!$B$6),"") | I97: 1 | J97: =IF(F97="Monthly interest",MAX(0,Assumptions!$B$5-I97),"") -> 2 | K97: =IF(F97="Bullet",G97*AD97,MAX(I97,1)*AD97) -> 1835 | L97: 46274 | M97: Low | N97: Voice bot | O97: Escalated: no response on whatsapp reminder | P97: WhatsApp reminder | Q97: A - Regular monthly payer | R97: Gentle reminder + eNACH nudge | S97: Tamil | T97: Y | U97: Evening (4-8pm) | V97: Tamil Nadu | W97: Coimbatore | X97: Coimbatore - Church Road | Y97: GL7642466325 | Z97: 46121 | AA97: 12 | AB97: =EDATE(Z97,AA97) -> 46486 | AC97: 16 | AD97: =ROUND(D97*AC97/100/12,0) -> 1835 | AE97: =IF(F97="Bullet",H97*AD97,MIN(MAX(I97,1),Assumptions!$B$6)*AD97) -> 1835 | AF97: =IF(F97="Bullet",MAX(0,Assumptions!$B$4-AB97),MAX(0,Assumptions!$B$4-L97)) -> 24 | AG97: 46248 | AH97: =IF(AG97="","",Assumptions!$B$4-AG97) -> 50 | AI97: Y | AJ97: 1 | AK97: 1 | AL97: NA | AM97: 0 | AN97: N | AO97: 65.9 | AP97: 22 | AQ97: 46291 | AR97: WhatsApp reminder | AS97: No response
A98: MFLC1000097 | B98: Ravi Setty | C98: 9429085620 | D98: 216400 | E98: Gold loan | F98: Bullet | G98: 1 | H98: =IF(F98="Bullet",MIN(G98,Assumptions!$B$6),"") -> 1 | J98: =IF(F98="Monthly interest",MAX(0,Assumptions!$B$5-I98),"") | K98: =IF(F98="Bullet",G98*AD98,MAX(I98,1)*AD98) -> 2344 | L98: 46263 | M98: Low | N98: WhatsApp reminder | O98: Early-stage delinquency: matched to risk and ticket size | P98: Voice bot | Q98: E - Other early delinquent | R98: Reminder + payment link | S98: Telugu | T98: Y | U98: Morning (9am-12pm) | V98: Telangana | W98: Nizamabad | X98: Nizamabad - Temple Street | Y98: GL0416306917 | Z98: 46263 | AA98: 6 | AB98: =EDATE(Z98,AA98) -> 46446 | AC98: 13 | AD98: =ROUND(D98*AC98/100/12,0) -> 2344 | AE98: =IF(F98="Bullet",H98*AD98,MIN(MAX(I98,1),Assumptions!$B$6)*AD98) -> 2344 | AF98: =IF(F98="Bullet",MAX(0,Assumptions!$B$4-AB98),MAX(0,Assumptions!$B$4-L98)) -> 0 | AH98: =IF(AG98="","",Assumptions!$B$4-AG98) | AI98: NA | AK98: 1 | AL98: 623 | AM98: 1 | AN98: N | AO98: 61.3 | AP98: 14 | AQ98: 46276 | AR98: Call center | AS98: No response
A99: MFLC1000098 | B99: Dinesh Raman | C99: 9598690858 | D99: 66800 | E99: Gold loan | F99: Bullet | G99: 4 | H99: =IF(F99="Bullet",MIN(G99,Assumptions!$B$6),"") -> 2 | J99: =IF(F99="Monthly interest",MAX(0,Assumptions!$B$5-I99),"") | K99: =IF(F99="Bullet",G99*AD99,MAX(I99,1)*AD99) -> 3116 | L99: 46170 | M99: Medium | N99: Voice bot | O99: Early-stage delinquency: matched to risk and ticket size | P99: Call center | Q99: E - Other early delinquent | R99: Reminder + payment link | S99: Tamil | T99: Y | U99: Morning (9am-12pm) | V99: Tamil Nadu | W99: Vellore | X99: Vellore - Church Road | Y99: GL4096544248 | Z99: 46170 | AA99: 12 | AB99: =EDATE(Z99,AA99) -> 46535 | AC99: 14 | AD99: =ROUND(D99*AC99/100/12,0) -> 779 | AE99: =IF(F99="Bullet",H99*AD99,MIN(MAX(I99,1),Assumptions!$B$6)*AD99) -> 1558 | AF99: =IF(F99="Bullet",MAX(0,Assumptions!$B$4-AB99),MAX(0,Assumptions!$B$4-L99)) -> 0 | AH99: =IF(AG99="","",Assumptions!$B$4-AG99) | AI99: NA | AK99: 2 | AL99: 719 | AM99: 1 | AN99: N | AO99: 65.1 | AP99: 31 | AQ99: 46293 | AR99: Voice bot | AS99: Promised to pay
A100: MFLC1000099 | B100: Sanjay Mishra | C100: 9091578108 | D100: 229800 | E100: Gold loan | F100: Monthly interest | H100: =IF(F100="Bullet",MIN(G100,Assumptions!$B$6),"") | I100: 2 | J100: =IF(F100="Monthly interest",MAX(0,Assumptions!$B$5-I100),"") -> 1 | K100: =IF(F100="Bullet",G100*AD100,MAX(I100,1)*AD100) -> 9192 | L100: 46262 | M100: Medium | N100: Call center | O100: Early-stage delinquency: matched to risk and ticket size | P100: Field visit | Q100: E - Other early delinquent | R100: Reminder + payment link | S100: Hindi | T100: Y | U100: Afternoon (12-4pm) | V100: Uttar Pradesh | W100: Noida | X100: Noida - Bus Stand | Y100: GL6068540322 | Z100: 46140 | AA100: 12 | AB100: =EDATE(Z100,AA100) -> 46505 | AC100: 24 | AD100: =ROUND(D100*AC100/100/12,0) -> 4596 | AE100: =IF(F100="Bullet",H100*AD100,MIN(MAX(I100,1),Assumptions!$B$6)*AD100) -> 9192 | AF100: =IF(F100="Bullet",MAX(0,Assumptions!$B$4-AB100),MAX(0,Assumptions!$B$4-L100)) -> 36 | AG100: 46235 | AH100: =IF(AG100="","",Assumptions!$B$4-AG100) -> 63 | AI100: N | AJ100: 3 | AK100: 1 | AL100: 735 | AM100: 0 | AN100: N | AO100: 73.9 | AP100: 43 | AQ100: 46284 | AR100: WhatsApp reminder | AS100: No response
...

Sheet Summary
A1: Summary of sample collections pool (2,000 gold loan customers)
A2: All figures are live COUNTIFS/SUMIFS on the Customers sheet.
A4: By payment scheme
A5: Payment scheme | B5: Customers | C5: % of total | D5: Total POS (₹) | E5: Total due (₹)
A6: Bullet | B6: =COUNTIF(Customers!$F$2:$F$2001,A6) -> 874 | C6: =B6/COUNTA(Customers!$A$2:$A$2001) -> 0.437 | D6: =SUMIFS(Customers!$D$2:$D$2001,Customers!$F$2:$F$2001,A6) -> 158403400 | E6: =SUMIFS(Customers!$K$2:$K$2001,Customers!$F$2:$F$2001,A6) -> 6450692
A7: Monthly interest | B7: =COUNTIF(Customers!$F$2:$F$2001,A7) -> 1126 | C7: =B7/COUNTA(Customers!$A$2:$A$2001) -> 0.563 | D7: =SUMIFS(Customers!$D$2:$D$2001,Customers!$F$2:$F$2001,A7) -> 205733600 | E7: =SUMIFS(Customers!$K$2:$K$2001,Customers!$F$2:$F$2001,A7) -> 4560693
A8: Total | B8: =SUM(B6:B7) -> 2000 | C8: =SUM(C6:C7) -> 1 | D8: =SUM(D6:D7) -> 364137000 | E8: =SUM(E6:E7) -> 11011385
A10: By risk tier
A11: Risk tier | B11: Customers | C11: % of total | D11: Total POS (₹) | E11: Total due (₹)
A12: High | B12: =COUNTIF(Customers!$M$2:$M$2001,A12) -> 519 | C12: =B12/COUNTA(Customers!$A$2:$A$2001) -> 0.2595 | D12: =SUMIFS(Customers!$D$2:$D$2001,Customers!$M$2:$M$2001,A12) -> 97141200 | E12: =SUMIFS(Customers!$K$2:$K$2001,Customers!$M$2:$M$2001,A12) -> 4057076
A13: Medium | B13: =COUNTIF(Customers!$M$2:$M$2001,A13) -> 688 | C13: =B13/COUNTA(Customers!$A$2:$A$2001) -> 0.344 | D13: =SUMIFS(Customers!$D$2:$D$2001,Customers!$M$2:$M$2001,A13) -> 124490900 | E13: =SUMIFS(Customers!$K$2:$K$2001,Customers!$M$2:$M$2001,A13) -> 3843687
A14: Low | B14: =COUNTIF(Customers!$M$2:$M$2001,A14) -> 793 | C14: =B14/COUNTA(Customers!$A$2:$A$2001) -> 0.3965 | D14: =SUMIFS(Customers!$D$2:$D$2001,Customers!$M$2:$M$2001,A14) -> 142504900 | E14: =SUMIFS(Customers!$K$2:$K$2001,Customers!$M$2:$M$2001,A14) -> 3110622
A16: By suggested channel
A17: Suggested channel | B17: Customers | C17: % of total | D17: Total POS (₹) | E17: Total due (₹)
A18: WhatsApp reminder | B18: =COUNTIF(Customers!$N$2:$N$2001,A18) -> 509 | C18: =B18/COUNTA(Customers!$A$2:$A$2001) -> 0.2545 | D18: =SUMIFS(Customers!$D$2:$D$2001,Customers!$N$2:$N$2001,A18) -> 91034300 | E18: =SUMIFS(Customers!$K$2:$K$2001,Customers!$N$2:$N$2001,A18) -> 1564057
A19: Voice bot | B19: =COUNTIF(Customers!$N$2:$N$2001,A19) -> 772 | C19: =B19/COUNTA(Customers!$A$2:$A$2001) -> 0.386 | D19: =SUMIFS(Customers!$D$2:$D$2001,Customers!$N$2:$N$2001,A19) -> 119872900 | E19: =SUMIFS(Customers!$K$2:$K$2001,Customers!$N$2:$N$2001,A19) -> 3378410
A20: Bot + call center | B20: =COUNTIF(Customers!$N$2:$N$2001,A20) -> 519 | C20: =B20/COUNTA(Customers!$A$2:$A$2001) -> 0.2595 | D20: =SUMIFS(Customers!$D$2:$D$2001,Customers!$N$2:$N$2001,A20) -> 97141200 | E20: =SUMIFS(Customers!$K$2:$K$2001,Customers!$N$2:$N$2001,A20) -> 4057076
A21: Call center | B21: =COUNTIF(Customers!$N$2:$N$2001,A21) -> 200 | C21: =B21/COUNTA(Customers!$A$2:$A$2001) -> 0.1 | D21: =SUMIFS(Customers!$D$2:$D$2001,Customers!$N$2:$N$2001,A21) -> 56088600 | E21: =SUMIFS(Customers!$K$2:$K$2001,Customers!$N$2:$N$2001,A21) -> 2011842
A23: Treatment segment x suggested channel (customers)
A24: Treatment segment | B24: WhatsApp reminder | C24: Voice bot | D24: Bot + call center | E24: Call center | F24: Total
A25: A - Regular monthly payer | B25: =COUNTIFS(Customers!$Q$2:$Q$2001,$A25,Customers!$N$2:$N$2001,B$24) -> 309 | C25: =COUNTIFS(Customers!$Q$2:$Q$2001,$A25,Customers!$N$2:$N$2001,C$24) -> 215 | D25: =COUNTIFS(Customers!$Q$2:$Q$2001,$A25,Customers!$N$2:$N$2001,D$24) -> 0 | E25: =COUNTIFS(Customers!$Q$2:$Q$2001,$A25,Customers!$N$2:$N$2001,E$24) -> 0 | F25: =SUM(B25:E25) -> 524
A26: B - Small-ticket | B26: =COUNTIFS(Customers!$Q$2:$Q$2001,$A26,Customers!$N$2:$N$2001,B$24) -> 62 | C26: =COUNTIFS(Customers!$Q$2:$Q$2001,$A26,Customers!$N$2:$N$2001,C$24) -> 161 | D26: =COUNTIFS(Customers!$Q$2:$Q$2001,$A26,Customers!$N$2:$N$2001,D$24) -> 53 | E26: =COUNTIFS(Customers!$Q$2:$Q$2001,$A26,Customers!$N$2:$N$2001,E$24) -> 0 | F26: =SUM(B26:E26) -> 276
A27: C - Accrued bullet | B27: =COUNTIFS(Customers!$Q$2:$Q$2001,$A27,Customers!$N$2:$N$2001,B$24) -> 0 | C27: =COUNTIFS(Customers!$Q$2:$Q$2001,$A27,Customers!$N$2:$N$2001,C$24) -> 53 | D27: =COUNTIFS(Customers!$Q$2:$Q$2001,$A27,Customers!$N$2:$N$2001,D$24) -> 167 | E27: =COUNTIFS(Customers!$Q$2:$Q$2001,$A27,Customers!$N$2:$N$2001,E$24) -> 11 | F27: =SUM(B27:E27) -> 231
A28: D - Bouncing EII | B28: =COUNTIFS(Customers!$Q$2:$Q$2001,$A28,Customers!$N$2:$N$2001,B$24) -> 0 | C28: =COUNTIFS(Customers!$Q$2:$Q$2001,$A28,Customers!$N$2:$N$2001,C$24) -> 0 | D28: =COUNTIFS(Customers!$Q$2:$Q$2001,$A28,Customers!$N$2:$N$2001,D$24) -> 244 | E28: =COUNTIFS(Customers!$Q$2:$Q$2001,$A28,Customers!$N$2:$N$2001,E$24) -> 0 | F28: =SUM(B28:E28) -> 244
A29: E - Other early delinquent | B29: =COUNTIFS(Customers!$Q$2:$Q$2001,$A29,Customers!$N$2:$N$2001,B$24) -> 138 | C29: =COUNTIFS(Customers!$Q$2:$Q$2001,$A29,Customers!$N$2:$N$2001,C$24) -> 343 | D29: =COUNTIFS(Customers!$Q$2:$Q$2001,$A29,Customers!$N$2:$N$2001,D$24) -> 55 | E29: =COUNTIFS(Customers!$Q$2:$Q$2001,$A29,Customers!$N$2:$N$2001,E$24) -> 189 | F29: =SUM(B29:E29) -> 725
A30: Total | B30: =SUM(B25:B29) -> 509 | C30: =SUM(C25:C29) -> 772 | D30: =SUM(D25:D29) -> 519 | E30: =SUM(E25:E29) -> 200 | F30: =SUM(F25:F29) -> 2000
A32: Monthly-interest customers by months unpaid (NPA at 3 months)
A33: Months unpaid | B33: Months to NPA | C33: Customers | D33: % of monthly-interest customers
A34: 1 | B34: =Assumptions!$B$5-A34 -> 2 | C34: =COUNTIF(Customers!$I$2:$I$2001,A34) -> 638 | D34: =C34/SUM($C$34:$C$35) -> 0.56660746
A35: 2 | B35: =Assumptions!$B$5-A35 -> 1 | C35: =COUNTIF(Customers!$I$2:$I$2001,A35) -> 488 | D35: =C35/SUM($C$34:$C$35) -> 0.43339254
A36: eNACH registered (monthly-interest) | C36: =COUNTIFS(Customers!$F$2:$F$2001,"Monthly interest",Customers!$AI$2:$AI$2001,"Y") -> 344 | D36: =C36/SUM($C$34:$C$35) -> 0.30550622
A38: By fallback channel
A39: Fallback channel | B39: Customers | C39: % of total
A40: Voice bot | B40: =COUNTIF(Customers!$P$2:$P$2001,A40) -> 509 | C40: =B40/COUNTA(Customers!$A$2:$A$2001) -> 0.2545
A41: WhatsApp reminder | B41: =COUNTIF(Customers!$P$2:$P$2001,A41) -> 178 | C41: =B41/COUNTA(Customers!$A$2:$A$2001) -> 0.089
A42: Call center | B42: =COUNTIF(Customers!$P$2:$P$2001,A42) -> 433 | C42: =B42/COUNTA(Customers!$A$2:$A$2001) -> 0.2165
A43: Field visit | B43: =COUNTIF(Customers!$P$2:$P$2001,A43) -> 719 | C43: =B43/COUNTA(Customers!$A$2:$A$2001) -> 0.3595
A44: None - bot retry cadence | B44: =COUNTIF(Customers!$P$2:$P$2001,A44) -> 161 | C44: =B44/COUNTA(Customers!$A$2:$A$2001) -> 0.0805
A47: By preferred language (voice bot / WhatsApp)
A48: Language | B48: Customers | C48: % of total
A49: Malayalam | B49: =COUNTIF(Customers!$S$2:$S$2001,A49) -> 421 | C49: =B49/COUNTA(Customers!$A$2:$A$2001) -> 0.2105
A50: Tamil | B50: =COUNTIF(Customers!$S$2:$S$2001,A50) -> 386 | C50: =B50/COUNTA(Customers!$A$2:$A$2001) -> 0.193
A51: Kannada | B51: =COUNTIF(Customers!$S$2:$S$2001,A51) -> 273 | C51: =B51/COUNTA(Customers!$A$2:$A$2001) -> 0.1365
A52: Telugu | B52: =COUNTIF(Customers!$S$2:$S$2001,A52) -> 346 | C52: =B52/COUNTA(Customers!$A$2:$A$2001) -> 0.173
A53: Hindi | B53: =COUNTIF(Customers!$S$2:$S$2001,A53) -> 428 | C53: =B53/COUNTA(Customers!$A$2:$A$2001) -> 0.214
A54: English | B54: =COUNTIF(Customers!$S$2:$S$2001,A54) -> 146 | C54: =B54/COUNTA(Customers!$A$2:$A$2001) -> 0.073

Sheet Assumptions
A1: Assumptions, rules and notes
A2: Yellow cells B4:B6 are live inputs used by formulas on the Customers sheet. B7:B10 are documented cut-offs that were applied when the static columns (risk tier, segment, channel) were built; changing them does not recalculate those columns.
A3: Parameter | B3: Value | C3: Used by / note
A4: As-of date | B4: 46298 | C4: Reference date for days past due and days since last payment. Assumption: today's date.
A5: NPA trigger (months of unpaid interest) | B5: 3 | C5: Per your input: if interest is unpaid for 3 months the account turns NPA. Drives "Monthly: months to NPA" = trigger - months unpaid. Every monthly-interest account in the sample has 1-2 months unpaid, so months to NPA is always 1 or 2. Static risk tier/channel columns do NOT recalc if this changes.
A6: Max months of interest the bot asks for (minimum amount due) | B6: 2 | C6: Drives "Bullet: months bot should try to collect" and "Bot ask amount". Based on your example of securing 2 months of pending interest.
A7: Small-ticket POS threshold (₹) | B7: 50000 | C7: Used to assign segment B and to size the channel (documented; values on Customers are static).
A8: Large-ticket POS threshold (₹) | B8: 200000 | C8: Used in channel logic for large-ticket customers (documented; values on Customers are static).
A9: Risk tier cut-off: Medium from score | B9: 31 | C9: Score below this = Low. Cut-offs set so roughly 40% Low / 34% Medium / 26% High.
A10: Risk tier cut-off: High from score | B10: 48 | C10: Score at or above this = High.
A13: Treatment segments (rule order: first match wins)
A14: C - Accrued bullet | B14: Bullet scheme with 5-6 months of interest accrued | C14: Bot negotiates a minimum amount due
A15: D - Bouncing EII | B15: Monthly-interest, POS >= ₹50k and risk = High | C15: Bot + call center
A16: B - Small-ticket | B16: POS < ₹50k (not already C) | C16: Bot/digital reminders; call center added only if risk = High
A17: A - Regular monthly payer | B17: Monthly-interest, POS >= ₹50k, 1 month unpaid (just slipped), risk not High | C17: WhatsApp nudge; push eNACH
A18: E - Other early delinquent | B18: Everything else (ADDED by me; you defined A-D only) | C18: Matched to risk tier and ticket size
A20: Suggested channel logic (base rule, then response-based reallocation, then consent check)
A21: RULE 1 - High risk | B21: Every High-risk customer is "Bot + call center": the voice bot goes first and the call center follows up (non-responders, negotiation, promise-to-pay). Applies to all segments.
A22: A | B22: WhatsApp reminder
A23: B (not High risk) | B23: WhatsApp reminder if 1 month unpaid, else Voice bot
A24: C (not High risk) | B24: Voice bot negotiates the minimum amount due
A25: E (not High risk) | B25: Low risk: WhatsApp reminder (Voice bot if 3+ months of bullet interest) | Medium risk: Voice bot; Call center if POS > ₹2L and urgent (monthly with 2 months unpaid, or bullet with 3+ months)
A26: Reallocation on response | B26: Non-High-risk customers: if the last attempt used the same channel and got No response / Not reachable, move one rung up (WhatsApp > Voice bot > Call center), capped per segment (A, B: Voice bot; C, E: Call center). Refused / disputed goes to Call center (not A, B).
A27: Consent check | B27: If WhatsApp is the suggested channel but WhatsApp opt-in = N, route to Voice bot.
A28: Fallback channel | B28: WhatsApp > Voice bot | Voice bot > WhatsApp (Low risk with opt-in), None for segment B, else Call center | Call center and Bot + call center > Field visit
A29: Field visit | B29: No longer a first-line channel. It is the fallback after Bot + call center / Call center. Tell me if you want it back as a first-line channel for the highest-urgency accounts.
A31: How the sample data was generated (all values are synthetic)
A32: Mobile numbers / names | B32: Randomly generated and fictitious. Random 10-digit numbers could belong to real people: replace with test numbers before any live voice-bot or WhatsApp trial.
A33: Payment scheme mix | B33: ~56% Monthly interest, ~44% Bullet. Bullet tenures: 3M 12%, 6M 58%, 12M 30% (6M largest, as in the Bullet 3M/6M/12M cut on your collections page).
A34: Months unpaid (monthly) | B34: 1 month: ~57%, 2 months: ~43%. Accounts with 0 months unpaid (not yet due) are excluded, so every monthly-interest account is within 1-2 months of NPA (3-month trigger). This is the at-risk collections pool, consistent with your "20-40% of EII loans at risk of NPA in 3 months".
A35: eNACH | B35: ~30% of monthly-interest loans have eNACH, i.e. ~70% do not (your 60-80% without NACH).
A36: POS | B36: Log-normal, median ~₹1.2L, range ₹15k to ₹25L.
A37: Interest rate | B37: Bullet 12-18% p.a.; Monthly interest 14-24% p.a. (illustrative, not Muthoot's rate card).
A38: Risk score | B38: Weighted on-us behaviour (months unpaid, missed payments, broken promises; for bullets, accrual months and maturity pressure), off-us signals (bureau score, off-us loans, off-us delinquency) and LTV, plus noise. Scaled 0-100. Bullets are not subject to the 3-month NPA clock (bullet NPA depends on maturity), so their months of interest due can run to 6.
A39: Static vs formula columns | B39: Green headers on Customers are live formulas (due amount, months to NPA, bot ask, days past due, maturity). Risk score, risk tier, segment, channel and fallback are static model-style outputs.

Sheet Data dictionary
A1: Data dictionary
A2: Navy headers = columns you asked for. Blue = columns I added. Teal = live formula columns.
A4: # | B4: Column | C4: Requested / Added | D4: Type | E4: Description
A5: 1 | B5: Customer ID | C5: Requested | D5: Data | E5: Unique customer identifier (synthetic).
A6: 2 | B6: Customer name | C6: Requested | D6: Data | E6: Customer name (synthetic, matched to state/language).
A7: 3 | B7: Mobile no. | C7: Requested | D7: Data | E7: 10-digit mobile number (synthetic). Do not dial.
A8: 4 | B8: POS (₹) | C8: Requested | D8: Data | E8: Principal outstanding on the gold loan, in ₹.
A9: 5 | B9: Loan type | C9: Requested | D9: Data | E9: Loan type. All rows are Gold loan.
A10: 6 | B10: Payment scheme | C10: Requested | D10: Data | E10: Bullet (interest + principal at maturity) or Monthly interest (EII).
A11: 7 | B11: Bullet: months of interest due | C11: Requested | D11: Data | E11: Bullet only: months of interest accrued and unpaid.
A12: 8 | B12: Bullet: months bot should try to collect | C12: Requested | D12: Formula | E12: Bullet only: months of interest the bot tries to collect = MIN(months due, max months on Assumptions).
A13: 9 | B13: Monthly: months of interest unpaid | C13: Requested | D13: Data | E13: Monthly-interest only: months of interest not paid.
A14: 10 | B14: Monthly: months to NPA | C14: Requested | D14: Formula | E14: Monthly-interest only: months left before NPA = NPA trigger (3 months) - months unpaid, so always 1 or 2 in this sample.
A15: 11 | B15: Due amount (₹) | C15: Requested | D15: Formula | E15: Months of interest due x monthly interest. For monthly customers who are current (0 months unpaid), shows the upcoming month's interest.
A16: 12 | B16: Due since | C16: Requested | D16: Data | E16: Monthly: date of the oldest unpaid due date (or the upcoming due date if current). Bullet: date interest started accruing (loan start).
... A49: 45 | B49: Last contact outcome | C49: Added | D49: Data | E49: Outcome of the most recent contact.
